<?xml version="1.0" encoding="UTF-8" standalone="yes" ?><?expression media exportversion="1.0" appversion="1.0" ?><CatalogType>	<Catalog pathType = "MAC">m000002608</Catalog>	<MediaItemList>		<MediaItem>			<AssetProperties>				<Filename>m000002608_0001.tif</Filename>				<Filepath>DSSR:scan:10_raw:m000002608:m000002608_0001.tif</Filepath>				<UniqueID>1</UniqueID>				<Label>0</Label>				<Rating>0</Rating>				<MediaType>TIFF</MediaType>				<FileSize unit="Bytes">169259912</FileSize>				<Created>2008:07:02 15:14:36</Created>				<Modified>2008:07:02 15:14:42</Modified>				<Added>2008:07:08 11:39:51</Added>				<Annotated>2008:07:08 12:11:51</Annotated>			<ThumbnailSource>Thumbnails_(m000002608):m000002608_0001.jpg</ThumbnailSource>			</AssetProperties>			<MediaProperties>				<Width unit="Pixels">6488</Width>				<Height unit="Pixels">8696</Height>				<Resolution unit="DPI">600</Resolution>				<Depth unit="Bits">24</Depth>				<ViewRotation>1</ViewRotation>				<SampleColor>R:B0 G:D0 B:90</SampleColor>				<Pages>1</Pages>				<ColorSpace>RGB </ColorSpace>				<Compression>65537</Compression>				<PrimaryEncoding>TIFF (Uncompressed)</PrimaryEncoding>				<ColorProfile>Adobe RGB (1998)</ColorProfile>			</MediaProperties>			<AnnotationFields>				<Headline>Front Page</Headline>			</AnnotationFields>			<MetaDataFields>				<Maker>i2s Digibook Scanner</Maker>				<Model>Suprascan 10000 RGB</Model>				<Software>Digibook Version :5, 5, 0, 23</Software>				<SourceURL></SourceURL>			</MetaDataFields>		</MediaItem>		<MediaItem>			<AssetProperties>				<Filename>m000002608_0002.tif</Filename>				<Filepath>DSSR:scan:10_raw:m000002608:m000002608_0002.tif</Filepath>				<UniqueID>2</UniqueID>				<Label>0</Label>				<Rating>0</Rating>				<MediaType>TIFF</MediaType>				<FileSize unit="Bytes">170349896</FileSize>				<Created>2008:07:02 15:15:52</Created>				<Modified>2008:07:02 15:15:58</Modified>				<Added>2008:07:08 11:39:51</Added>				<Annotated>2008:07:08 12:11:57</Annotated>			<ThumbnailSource>Thumbnails_(m000002608):m000002608_0002.jpg</ThumbnailSource>			</AssetProperties>			<MediaProperties>				<Width unit="Pixels">6488</Width>				<Height unit="Pixels">8752</Height>				<Resolution unit="DPI">600</Resolution>				<Depth unit="Bits">24</Depth>				<ViewRotation>1</ViewRotation>				<SampleColor>R:C0 G:D0 B:A0</SampleColor>				<Pages>1</Pages>				<ColorSpace>RGB </ColorSpace>				<Compression>65537</Compression>				<PrimaryEncoding>TIFF (Uncompressed)</PrimaryEncoding>				<ColorProfile>Adobe RGB (1998)</ColorProfile>			</MediaProperties>			<AnnotationFields>				<Headline>Title Page</Headline>			</AnnotationFields>			<MetaDataFields>				<Maker>i2s Digibook Scanner</Maker>				<Model>Suprascan 10000 RGB</Model>				<Software>Digibook Version :5, 5, 0, 23</Software>				<SourceURL></SourceURL>			</MetaDataFields>		</MediaItem>		<MediaItem>			<AssetProperties>				<Filename>m000002608_0003.tif</Filename>				<Filepath>DSSR:scan:10_raw:m000002608:m000002608_0003.tif</Filepath>				<UniqueID>3</UniqueID>				<Label>0</Label>				<Rating>0</Rating>				<MediaType>TIFF</MediaType>				<FileSize unit="Bytes">169886024</FileSize>				<Created>2008:07:02 15:15:58</Created>				<Modified>2008:07:02 15:16:04</Modified>				<Added>2008:07:08 11:39:51</Added>				<Annotated>2008:07:08 12:12:01</Annotated>			<ThumbnailSource>Thumbnails_(m000002608):m000002608_0003.jpg</ThumbnailSource>			</AssetProperties>			<MediaProperties>				<Width unit="Pixels">6512</Width>				<Height unit="Pixels">8696</Height>				<Resolution unit="DPI">600</Resolution>				<Depth unit="Bits">24</Depth>				<ViewRotation>1</ViewRotation>				<SampleColor>R:C0 G:D0 B:A0</SampleColor>				<Pages>1</Pages>				<ColorSpace>RGB </ColorSpace>				<Compression>65537</Compression>				<PrimaryEncoding>TIFF (Uncompressed)</PrimaryEncoding>				<ColorProfile>Adobe RGB (1998)</ColorProfile>			</MediaProperties>			<AnnotationFields>				<Headline>Page 3</Headline>			</AnnotationFields>			<MetaDataFields>				<Maker>i2s Digibook Scanner</Maker>				<Model>Suprascan 10000 RGB</Model>				<Software>Digibook Version :5, 5, 0, 23</Software>				<SourceURL></SourceURL>			</MetaDataFields>		</MediaItem>		<MediaItem>			<AssetProperties>				<Filename>m000002608_0004.tif</Filename>				<Filepath>DSSR:scan:10_raw:m000002608:m000002608_0004.tif</Filepath>				<UniqueID>4</UniqueID>				<Label>0</Label>				<Rating>0</Rating>				<MediaType>TIFF</MediaType>				<FileSize unit="Bytes">170349896</FileSize>				<Created>2008:07:02 15:17:27</Created>				<Modified>2008:07:02 15:17:35</Modified>				<Added>2008:07:08 11:39:51</Added>				<Annotated>2008:07:08 12:12:04</Annotated>			<ThumbnailSource>Thumbnails_(m000002608):m000002608_0004.jpg</ThumbnailSource>			</AssetProperties>			<MediaProperties>				<Width unit="Pixels">6488</Width>				<Height unit="Pixels">8752</Height>				<Resolution unit="DPI">600</Resolution>				<Depth unit="Bits">24</Depth>				<ViewRotation>1</ViewRotation>				<SampleColor>R:B0 G:D0 B:90</SampleColor>				<Pages>1</Pages>				<ColorSpace>RGB </ColorSpace>				<Compression>65537</Compression>				<PrimaryEncoding>TIFF (Uncompressed)</PrimaryEncoding>				<ColorProfile>Adobe RGB (1998)</ColorProfile>			</MediaProperties>			<AnnotationFields>				<Headline>Back Page</Headline>			</AnnotationFields>			<MetaDataFields>				<Maker>i2s Digibook Scanner</Maker>				<Model>Suprascan 10000 RGB</Model>				<Software>Digibook Version :5, 5, 0, 23</Software>				<SourceURL></SourceURL>			</MetaDataFields>		</MediaItem>	</MediaItemList></CatalogType>