<?xml version="1.0" encoding="UTF-8" standalone="yes" ?><?expression media exportversion="1.0" appversion="1.0" ?><CatalogType>	<Catalog pathType = "MAC">m000003027</Catalog>	<MediaItemList>		<MediaItem>			<AssetProperties>				<Filename>m000003027_0001.tif</Filename>				<Filepath>DSSR:scan:10_raw:m000003027:m000003027_0001.tif</Filepath>				<UniqueID>1</UniqueID>				<Label>0</Label>				<Rating>0</Rating>				<MediaType>TIFF</MediaType>				<FileSize unit="Bytes">177071430</FileSize>				<Created>2008:07:11 10:12:38</Created>				<Modified>2008:07:11 10:12:47</Modified>				<Added>2008:07:11 11:20:51</Added>				<Annotated>2008:07:11 14:14:48</Annotated>			<ThumbnailSource>Thumbnails_(m000003027):m000003027_0001.jpg</ThumbnailSource>			</AssetProperties>			<MediaProperties>				<Width unit="Pixels">6744</Width>				<Height unit="Pixels">8752</Height>				<Resolution unit="DPI">600</Resolution>				<Depth unit="Bits">24</Depth>				<ViewRotation>1</ViewRotation>				<SampleColor>R:A0 G:C0 B:80</SampleColor>				<Pages>1</Pages>				<ColorSpace>RGB </ColorSpace>				<Compression>65537</Compression>				<PrimaryEncoding>TIFF (Uncompressed)</PrimaryEncoding>				<ColorProfile>Adobe RGB (1998)</ColorProfile>			</MediaProperties>			<AnnotationFields>				<Headline>Title Page</Headline>			</AnnotationFields>			<MetaDataFields>				<Maker>i2s Digibook Scanner</Maker>				<Model>Suprascan 10000 RGB</Model>				<Software>Digibook Version :5, 5, 8, 5</Software>				<SourceURL></SourceURL>			</MetaDataFields>		</MediaItem>		<MediaItem>			<AssetProperties>				<Filename>m000003027_0002.tif</Filename>				<Filepath>DSSR:scan:10_raw:m000003027:m000003027_0002.tif</Filepath>				<UniqueID>2</UniqueID>				<Label>0</Label>				<Rating>0</Rating>				<MediaType>TIFF</MediaType>				<FileSize unit="Bytes">173561286</FileSize>				<Created>2008:07:11 10:14:30</Created>				<Modified>2008:07:11 10:14:42</Modified>				<Added>2008:07:11 11:20:54</Added>				<Annotated>2008:07:11 14:14:50</Annotated>			<ThumbnailSource>Thumbnails_(m000003027):m000003027_0002.jpg</ThumbnailSource>			</AssetProperties>			<MediaProperties>				<Width unit="Pixels">6696</Width>				<Height unit="Pixels">8640</Height>				<Resolution unit="DPI">600</Resolution>				<Depth unit="Bits">24</Depth>				<ViewRotation>1</ViewRotation>				<SampleColor>R:B0 G:D0 B:90</SampleColor>				<Pages>1</Pages>				<ColorSpace>RGB </ColorSpace>				<Compression>65537</Compression>				<PrimaryEncoding>TIFF (Uncompressed)</PrimaryEncoding>				<ColorProfile>Adobe RGB (1998)</ColorProfile>			</MediaProperties>			<AnnotationFields>				<Headline>2</Headline>			</AnnotationFields>			<MetaDataFields>				<Maker>i2s Digibook Scanner</Maker>				<Model>Suprascan 10000 RGB</Model>				<Software>Digibook Version :5, 5, 8, 5</Software>				<SourceURL></SourceURL>			</MetaDataFields>		</MediaItem>		<MediaItem>			<AssetProperties>				<Filename>m000003027_0003.tif</Filename>				<Filepath>DSSR:scan:10_raw:m000003027:m000003027_0003.tif</Filepath>				<UniqueID>3</UniqueID>				<Label>0</Label>				<Rating>0</Rating>				<MediaType>TIFF</MediaType>				<FileSize unit="Bytes">177934854</FileSize>				<Created>2008:07:11 10:14:42</Created>				<Modified>2008:07:11 10:14:52</Modified>				<Added>2008:07:11 11:20:56</Added>				<Annotated>2008:07:11 14:14:53</Annotated>			<ThumbnailSource>Thumbnails_(m000003027):m000003027_0003.jpg</ThumbnailSource>			</AssetProperties>			<MediaProperties>				<Width unit="Pixels">6808</Width>				<Height unit="Pixels">8712</Height>				<Resolution unit="DPI">600</Resolution>				<Depth unit="Bits">24</Depth>				<ViewRotation>1</ViewRotation>				<SampleColor>R:B0 G:D0 B:90</SampleColor>				<Pages>1</Pages>				<ColorSpace>RGB </ColorSpace>				<Compression>65537</Compression>				<PrimaryEncoding>TIFF (Uncompressed)</PrimaryEncoding>				<ColorProfile>Adobe RGB (1998)</ColorProfile>			</MediaProperties>			<AnnotationFields>				<Headline>3</Headline>			</AnnotationFields>			<MetaDataFields>				<Maker>i2s Digibook Scanner</Maker>				<Model>Suprascan 10000 RGB</Model>				<Software>Digibook Version :5, 5, 8, 5</Software>				<SourceURL></SourceURL>			</MetaDataFields>		</MediaItem>		<MediaItem>			<AssetProperties>				<Filename>m000003027_0004.tif</Filename>				<Filepath>DSSR:scan:10_raw:m000003027:m000003027_0004.tif</Filepath>				<UniqueID>4</UniqueID>				<Label>0</Label>				<Rating>0</Rating>				<MediaType>TIFF</MediaType>				<FileSize unit="Bytes">178771206</FileSize>				<Created>2008:07:11 10:16:34</Created>				<Modified>2008:07:11 10:16:45</Modified>				<Added>2008:07:11 11:20:58</Added>				<Annotated>2008:07:11 14:14:54</Annotated>			<ThumbnailSource>Thumbnails_(m000003027):m000003027_0004.jpg</ThumbnailSource>			</AssetProperties>			<MediaProperties>				<Width unit="Pixels">6840</Width>				<Height unit="Pixels">8712</Height>				<Resolution unit="DPI">600</Resolution>				<Depth unit="Bits">24</Depth>				<ViewRotation>1</ViewRotation>				<SampleColor>R:B0 G:D0 B:90</SampleColor>				<Pages>1</Pages>				<ColorSpace>RGB </ColorSpace>				<Compression>65537</Compression>				<PrimaryEncoding>TIFF (Uncompressed)</PrimaryEncoding>				<ColorProfile>Adobe RGB (1998)</ColorProfile>			</MediaProperties>			<AnnotationFields>				<Headline>4</Headline>			</AnnotationFields>			<MetaDataFields>				<Maker>i2s Digibook Scanner</Maker>				<Model>Suprascan 10000 RGB</Model>				<Software>Digibook Version :5, 5, 8, 5</Software>				<SourceURL></SourceURL>			</MetaDataFields>		</MediaItem>		<MediaItem>			<AssetProperties>				<Filename>m000003027_0005.tif</Filename>				<Filepath>DSSR:scan:10_raw:m000003027:m000003027_0005.tif</Filepath>				<UniqueID>5</UniqueID>				<Label>0</Label>				<Rating>0</Rating>				<MediaType>TIFF</MediaType>				<FileSize unit="Bytes">179277702</FileSize>				<Created>2008:07:11 10:16:45</Created>				<Modified>2008:07:11 10:16:57</Modified>				<Added>2008:07:11 11:21:00</Added>				<Annotated>2008:07:11 14:14:57</Annotated>			<ThumbnailSource>Thumbnails_(m000003027):m000003027_0005.jpg</ThumbnailSource>			</AssetProperties>			<MediaProperties>				<Width unit="Pixels">6872</Width>				<Height unit="Pixels">8696</Height>				<Resolution unit="DPI">600</Resolution>				<Depth unit="Bits">24</Depth>				<ViewRotation>1</ViewRotation>				<SampleColor>R:B0 G:D0 B:90</SampleColor>				<Pages>1</Pages>				<ColorSpace>RGB </ColorSpace>				<Compression>65537</Compression>				<PrimaryEncoding>TIFF (Uncompressed)</PrimaryEncoding>				<ColorProfile>Adobe RGB (1998)</ColorProfile>			</MediaProperties>			<AnnotationFields>				<Headline>5</Headline>			</AnnotationFields>			<MetaDataFields>				<Maker>i2s Digibook Scanner</Maker>				<Model>Suprascan 10000 RGB</Model>				<Software>Digibook Version :5, 5, 8, 5</Software>				<SourceURL></SourceURL>			</MetaDataFields>		</MediaItem>		<MediaItem>			<AssetProperties>				<Filename>m000003027_0006.tif</Filename>				<Filepath>DSSR:scan:10_raw:m000003027:m000003027_0006.tif</Filepath>				<UniqueID>6</UniqueID>				<Label>0</Label>				<Rating>0</Rating>				<MediaType>TIFF</MediaType>				<FileSize unit="Bytes">177307590</FileSize>				<Created>2008:07:11 10:18:48</Created>				<Modified>2008:07:11 10:18:59</Modified>				<Added>2008:07:11 11:21:02</Added>				<Annotated>2008:07:11 14:14:57</Annotated>			<ThumbnailSource>Thumbnails_(m000003027):m000003027_0006.jpg</ThumbnailSource>			</AssetProperties>			<MediaProperties>				<Width unit="Pixels">6784</Width>				<Height unit="Pixels">8712</Height>				<Resolution unit="DPI">600</Resolution>				<Depth unit="Bits">24</Depth>				<ViewRotation>1</ViewRotation>				<SampleColor>R:B0 G:D0 B:90</SampleColor>				<Pages>1</Pages>				<ColorSpace>RGB </ColorSpace>				<Compression>65537</Compression>				<PrimaryEncoding>TIFF (Uncompressed)</PrimaryEncoding>				<ColorProfile>Adobe RGB (1998)</ColorProfile>			</MediaProperties>			<AnnotationFields>				<Headline>6</Headline>			</AnnotationFields>			<MetaDataFields>				<Maker>i2s Digibook Scanner</Maker>				<Model>Suprascan 10000 RGB</Model>				<Software>Digibook Version :5, 5, 8, 5</Software>				<SourceURL></SourceURL>			</MetaDataFields>		</MediaItem>		<MediaItem>			<AssetProperties>				<Filename>m000003027_0007.tif</Filename>				<Filepath>DSSR:scan:10_raw:m000003027:m000003027_0007.tif</Filepath>				<UniqueID>7</UniqueID>				<Label>0</Label>				<Rating>0</Rating>				<MediaType>TIFF</MediaType>				<FileSize unit="Bytes">178052166</FileSize>				<Created>2008:07:11 10:18:59</Created>				<Modified>2008:07:11 10:19:11</Modified>				<Added>2008:07:11 11:21:04</Added>				<Annotated>2008:07:11 14:15:00</Annotated>			<ThumbnailSource>Thumbnails_(m000003027):m000003027_0007.jpg</ThumbnailSource>			</AssetProperties>			<MediaProperties>				<Width unit="Pixels">6800</Width>				<Height unit="Pixels">8728</Height>				<Resolution unit="DPI">600</Resolution>				<Depth unit="Bits">24</Depth>				<ViewRotation>1</ViewRotation>				<SampleColor>R:B0 G:D0 B:90</SampleColor>				<Pages>1</Pages>				<ColorSpace>RGB </ColorSpace>				<Compression>65537</Compression>				<PrimaryEncoding>TIFF (Uncompressed)</PrimaryEncoding>				<ColorProfile>Adobe RGB (1998)</ColorProfile>			</MediaProperties>			<AnnotationFields>				<Headline>7</Headline>			</AnnotationFields>			<MetaDataFields>				<Maker>i2s Digibook Scanner</Maker>				<Model>Suprascan 10000 RGB</Model>				<Software>Digibook Version :5, 5, 8, 5</Software>				<SourceURL></SourceURL>			</MetaDataFields>		</MediaItem>		<MediaItem>			<AssetProperties>				<Filename>m000003027_0008.tif</Filename>				<Filepath>DSSR:scan:10_raw:m000003027:m000003027_0008.tif</Filepath>				<UniqueID>8</UniqueID>				<Label>0</Label>				<Rating>0</Rating>				<MediaType>TIFF</MediaType>				<FileSize unit="Bytes">180012102</FileSize>				<Created>2008:07:11 10:20:59</Created>				<Modified>2008:07:11 10:21:22</Modified>				<Added>2008:07:11 11:21:06</Added>				<Annotated>2008:07:11 14:15:01</Annotated>			<ThumbnailSource>Thumbnails_(m000003027):m000003027_0008.jpg</ThumbnailSource>			</AssetProperties>			<MediaProperties>				<Width unit="Pixels">6856</Width>				<Height unit="Pixels">8752</Height>				<Resolution unit="DPI">600</Resolution>				<Depth unit="Bits">24</Depth>				<ViewRotation>1</ViewRotation>				<SampleColor>R:B0 G:D0 B:90</SampleColor>				<Pages>1</Pages>				<ColorSpace>RGB </ColorSpace>				<Compression>65537</Compression>				<PrimaryEncoding>TIFF (Uncompressed)</PrimaryEncoding>				<ColorProfile>Adobe RGB (1998)</ColorProfile>			</MediaProperties>			<AnnotationFields>				<Headline>8</Headline>			</AnnotationFields>			<MetaDataFields>				<Maker>i2s Digibook Scanner</Maker>				<Model>Suprascan 10000 RGB</Model>				<Software>Digibook Version :5, 5, 8, 5</Software>				<SourceURL></SourceURL>			</MetaDataFields>		</MediaItem>		<MediaItem>			<AssetProperties>				<Filename>m000003027_0009.tif</Filename>				<Filepath>DSSR:scan:10_raw:m000003027:m000003027_0009.tif</Filepath>				<UniqueID>9</UniqueID>				<Label>0</Label>				<Rating>0</Rating>				<MediaType>TIFF</MediaType>				<FileSize unit="Bytes">178961862</FileSize>				<Created>2008:07:11 10:21:22</Created>				<Modified>2008:07:11 10:21:33</Modified>				<Added>2008:07:11 11:21:08</Added>				<Annotated>2008:07:11 14:15:04</Annotated>			<ThumbnailSource>Thumbnails_(m000003027):m000003027_0009.jpg</ThumbnailSource>			</AssetProperties>			<MediaProperties>				<Width unit="Pixels">6816</Width>				<Height unit="Pixels">8752</Height>				<Resolution unit="DPI">600</Resolution>				<Depth unit="Bits">24</Depth>				<ViewRotation>1</ViewRotation>				<SampleColor>R:B0 G:D0 B:90</SampleColor>				<Pages>1</Pages>				<ColorSpace>RGB </ColorSpace>				<Compression>65537</Compression>				<PrimaryEncoding>TIFF (Uncompressed)</PrimaryEncoding>				<ColorProfile>Adobe RGB (1998)</ColorProfile>			</MediaProperties>			<AnnotationFields>				<Headline>9</Headline>			</AnnotationFields>			<MetaDataFields>				<Maker>i2s Digibook Scanner</Maker>				<Model>Suprascan 10000 RGB</Model>				<Software>Digibook Version :5, 5, 8, 5</Software>				<SourceURL></SourceURL>			</MetaDataFields>		</MediaItem>		<MediaItem>			<AssetProperties>				<Filename>m000003027_0010.tif</Filename>				<Filepath>DSSR:scan:10_raw:m000003027:m000003027_0010.tif</Filepath>				<UniqueID>10</UniqueID>				<Label>0</Label>				<Rating>0</Rating>				<MediaType>TIFF</MediaType>				<FileSize unit="Bytes">178052166</FileSize>				<Created>2008:07:11 10:23:08</Created>				<Modified>2008:07:11 10:23:31</Modified>				<Added>2008:07:11 11:21:10</Added>				<Annotated>2008:07:11 14:15:05</Annotated>			<ThumbnailSource>Thumbnails_(m000003027):m000003027_0010.jpg</ThumbnailSource>			</AssetProperties>			<MediaProperties>				<Width unit="Pixels">6800</Width>				<Height unit="Pixels">8728</Height>				<Resolution unit="DPI">600</Resolution>				<Depth unit="Bits">24</Depth>				<ViewRotation>1</ViewRotation>				<SampleColor>R:B0 G:D0 B:90</SampleColor>				<Pages>1</Pages>				<ColorSpace>RGB </ColorSpace>				<Compression>65537</Compression>				<PrimaryEncoding>TIFF (Uncompressed)</PrimaryEncoding>				<ColorProfile>Adobe RGB (1998)</ColorProfile>			</MediaProperties>			<AnnotationFields>				<Headline>10</Headline>			</AnnotationFields>			<MetaDataFields>				<Maker>i2s Digibook Scanner</Maker>				<Model>Suprascan 10000 RGB</Model>				<Software>Digibook Version :5, 5, 8, 5</Software>				<SourceURL></SourceURL>			</MetaDataFields>		</MediaItem>		<MediaItem>			<AssetProperties>				<Filename>m000003027_0011.tif</Filename>				<Filepath>DSSR:scan:10_raw:m000003027:m000003027_0011.tif</Filepath>				<UniqueID>11</UniqueID>				<Label>0</Label>				<Rating>0</Rating>				<MediaType>TIFF</MediaType>				<FileSize unit="Bytes">178634694</FileSize>				<Created>2008:07:11 10:23:31</Created>				<Modified>2008:07:11 10:24:03</Modified>				<Added>2008:07:11 11:21:12</Added>				<Annotated>2008:07:11 14:15:08</Annotated>			<ThumbnailSource>Thumbnails_(m000003027):m000003027_0011.jpg</ThumbnailSource>			</AssetProperties>			<MediaProperties>				<Width unit="Pixels">6816</Width>				<Height unit="Pixels">8736</Height>				<Resolution unit="DPI">600</Resolution>				<Depth unit="Bits">24</Depth>				<ViewRotation>1</ViewRotation>				<SampleColor>R:B0 G:D0 B:90</SampleColor>				<Pages>1</Pages>				<ColorSpace>RGB </ColorSpace>				<Compression>65537</Compression>				<PrimaryEncoding>TIFF (Uncompressed)</PrimaryEncoding>				<ColorProfile>Adobe RGB (1998)</ColorProfile>			</MediaProperties>			<AnnotationFields>				<Headline>11</Headline>			</AnnotationFields>			<MetaDataFields>				<Maker>i2s Digibook Scanner</Maker>				<Model>Suprascan 10000 RGB</Model>				<Software>Digibook Version :5, 5, 8, 5</Software>				<SourceURL></SourceURL>			</MetaDataFields>		</MediaItem>		<MediaItem>			<AssetProperties>				<Filename>m000003027_0012.tif</Filename>				<Filepath>DSSR:scan:10_raw:m000003027:m000003027_0012.tif</Filepath>				<UniqueID>12</UniqueID>				<Label>0</Label>				<Rating>0</Rating>				<MediaType>TIFF</MediaType>				<FileSize unit="Bytes">178890054</FileSize>				<Created>2008:07:11 10:25:22</Created>				<Modified>2008:07:11 10:25:32</Modified>				<Added>2008:07:11 11:21:14</Added>				<Annotated>2008:07:11 14:15:09</Annotated>			<ThumbnailSource>Thumbnails_(m000003027):m000003027_0012.jpg</ThumbnailSource>			</AssetProperties>			<MediaProperties>				<Width unit="Pixels">6832</Width>				<Height unit="Pixels">8728</Height>				<Resolution unit="DPI">600</Resolution>				<Depth unit="Bits">24</Depth>				<ViewRotation>1</ViewRotation>				<SampleColor>R:B0 G:D0 B:90</SampleColor>				<Pages>1</Pages>				<ColorSpace>RGB </ColorSpace>				<Compression>65537</Compression>				<PrimaryEncoding>TIFF (Uncompressed)</PrimaryEncoding>				<ColorProfile>Adobe RGB (1998)</ColorProfile>			</MediaProperties>			<AnnotationFields>				<Headline>12</Headline>			</AnnotationFields>			<MetaDataFields>				<Maker>i2s Digibook Scanner</Maker>				<Model>Suprascan 10000 RGB</Model>				<Software>Digibook Version :5, 5, 8, 5</Software>				<SourceURL></SourceURL>			</MetaDataFields>		</MediaItem>		<MediaItem>			<AssetProperties>				<Filename>m000003027_0013.tif</Filename>				<Filepath>DSSR:scan:10_raw:m000003027:m000003027_0013.tif</Filepath>				<UniqueID>13</UniqueID>				<Label>0</Label>				<Rating>0</Rating>				<MediaType>TIFF</MediaType>				<FileSize unit="Bytes">178634694</FileSize>				<Created>2008:07:11 10:25:32</Created>				<Modified>2008:07:11 10:25:44</Modified>				<Added>2008:07:11 11:21:16</Added>				<Annotated>2008:07:11 14:15:12</Annotated>			<ThumbnailSource>Thumbnails_(m000003027):m000003027_0013.jpg</ThumbnailSource>			</AssetProperties>			<MediaProperties>				<Width unit="Pixels">6816</Width>				<Height unit="Pixels">8736</Height>				<Resolution unit="DPI">600</Resolution>				<Depth unit="Bits">24</Depth>				<ViewRotation>1</ViewRotation>				<SampleColor>R:B0 G:D0 B:90</SampleColor>				<Pages>1</Pages>				<ColorSpace>RGB </ColorSpace>				<Compression>65537</Compression>				<PrimaryEncoding>TIFF (Uncompressed)</PrimaryEncoding>				<ColorProfile>Adobe RGB (1998)</ColorProfile>			</MediaProperties>			<AnnotationFields>				<Headline>13</Headline>			</AnnotationFields>			<MetaDataFields>				<Maker>i2s Digibook Scanner</Maker>				<Model>Suprascan 10000 RGB</Model>				<Software>Digibook Version :5, 5, 8, 5</Software>				<SourceURL></SourceURL>			</MetaDataFields>		</MediaItem>		<MediaItem>			<AssetProperties>				<Filename>m000003027_0014.tif</Filename>				<Filepath>DSSR:scan:10_raw:m000003027:m000003027_0014.tif</Filepath>				<UniqueID>14</UniqueID>				<Label>0</Label>				<Rating>0</Rating>				<MediaType>TIFF</MediaType>				<FileSize unit="Bytes">179727942</FileSize>				<Created>2008:07:11 10:27:05</Created>				<Modified>2008:07:11 10:27:26</Modified>				<Added>2008:07:11 11:21:18</Added>				<Annotated>2008:07:11 14:15:15</Annotated>			<ThumbnailSource>Thumbnails_(m000003027):m000003027_0014.jpg</ThumbnailSource>			</AssetProperties>			<MediaProperties>				<Width unit="Pixels">6864</Width>				<Height unit="Pixels">8728</Height>				<Resolution unit="DPI">600</Resolution>				<Depth unit="Bits">24</Depth>				<ViewRotation>1</ViewRotation>				<SampleColor>R:B0 G:D0 B:90</SampleColor>				<Pages>1</Pages>				<ColorSpace>RGB </ColorSpace>				<Compression>65537</Compression>				<PrimaryEncoding>TIFF (Uncompressed)</PrimaryEncoding>				<ColorProfile>Adobe RGB (1998)</ColorProfile>			</MediaProperties>			<AnnotationFields>				<Headline>14</Headline>			</AnnotationFields>			<MetaDataFields>				<Maker>i2s Digibook Scanner</Maker>				<Model>Suprascan 10000 RGB</Model>				<Software>Digibook Version :5, 5, 8, 5</Software>				<SourceURL></SourceURL>			</MetaDataFields>		</MediaItem>		<MediaItem>			<AssetProperties>				<Filename>m000003027_0015.tif</Filename>				<Filepath>DSSR:scan:10_raw:m000003027:m000003027_0015.tif</Filepath>				<UniqueID>15</UniqueID>				<Label>0</Label>				<Rating>0</Rating>				<MediaType>TIFF</MediaType>				<FileSize unit="Bytes">178634694</FileSize>				<Created>2008:07:11 10:27:26</Created>				<Modified>2008:07:11 10:27:46</Modified>				<Added>2008:07:11 11:21:21</Added>				<Annotated>2008:07:11 14:15:18</Annotated>			<ThumbnailSource>Thumbnails_(m000003027):m000003027_0015.jpg</ThumbnailSource>			</AssetProperties>			<MediaProperties>				<Width unit="Pixels">6816</Width>				<Height unit="Pixels">8736</Height>				<Resolution unit="DPI">600</Resolution>				<Depth unit="Bits">24</Depth>				<ViewRotation>1</ViewRotation>				<SampleColor>R:B0 G:D0 B:90</SampleColor>				<Pages>1</Pages>				<ColorSpace>RGB </ColorSpace>				<Compression>65537</Compression>				<PrimaryEncoding>TIFF (Uncompressed)</PrimaryEncoding>				<ColorProfile>Adobe RGB (1998)</ColorProfile>			</MediaProperties>			<AnnotationFields>				<Headline>15</Headline>			</AnnotationFields>			<MetaDataFields>				<Maker>i2s Digibook Scanner</Maker>				<Model>Suprascan 10000 RGB</Model>				<Software>Digibook Version :5, 5, 8, 5</Software>				<SourceURL></SourceURL>			</MetaDataFields>		</MediaItem>		<MediaItem>			<AssetProperties>				<Filename>m000003027_0016.tif</Filename>				<Filepath>DSSR:scan:10_raw:m000003027:m000003027_0016.tif</Filepath>				<UniqueID>16</UniqueID>				<Label>0</Label>				<Rating>0</Rating>				<MediaType>TIFF</MediaType>				<FileSize unit="Bytes">179727942</FileSize>				<Created>2008:07:11 10:29:14</Created>				<Modified>2008:07:11 10:29:36</Modified>				<Added>2008:07:11 11:21:22</Added>				<Annotated>2008:07:11 14:15:20</Annotated>			<ThumbnailSource>Thumbnails_(m000003027):m000003027_0016.jpg</ThumbnailSource>			</AssetProperties>			<MediaProperties>				<Width unit="Pixels">6864</Width>				<Height unit="Pixels">8728</Height>				<Resolution unit="DPI">600</Resolution>				<Depth unit="Bits">24</Depth>				<ViewRotation>1</ViewRotation>				<SampleColor>R:B0 G:D0 B:90</SampleColor>				<Pages>1</Pages>				<ColorSpace>RGB </ColorSpace>				<Compression>65537</Compression>				<PrimaryEncoding>TIFF (Uncompressed)</PrimaryEncoding>				<ColorProfile>Adobe RGB (1998)</ColorProfile>			</MediaProperties>			<AnnotationFields>				<Headline>16</Headline>			</AnnotationFields>			<MetaDataFields>				<Maker>i2s Digibook Scanner</Maker>				<Model>Suprascan 10000 RGB</Model>				<Software>Digibook Version :5, 5, 8, 5</Software>				<SourceURL></SourceURL>			</MetaDataFields>		</MediaItem>		<MediaItem>			<AssetProperties>				<Filename>m000003027_0017.tif</Filename>				<Filepath>DSSR:scan:10_raw:m000003027:m000003027_0017.tif</Filepath>				<UniqueID>17</UniqueID>				<Label>0</Label>				<Rating>0</Rating>				<MediaType>TIFF</MediaType>				<FileSize unit="Bytes">176747718</FileSize>				<Created>2008:07:11 10:29:36</Created>				<Modified>2008:07:11 10:30:01</Modified>				<Added>2008:07:11 11:21:24</Added>				<Annotated>2008:07:11 14:15:23</Annotated>			<ThumbnailSource>Thumbnails_(m000003027):m000003027_0017.jpg</ThumbnailSource>			</AssetProperties>			<MediaProperties>				<Width unit="Pixels">6744</Width>				<Height unit="Pixels">8736</Height>				<Resolution unit="DPI">600</Resolution>				<Depth unit="Bits">24</Depth>				<ViewRotation>1</ViewRotation>				<SampleColor>R:B0 G:D0 B:90</SampleColor>				<Pages>1</Pages>				<ColorSpace>RGB </ColorSpace>				<Compression>65537</Compression>				<PrimaryEncoding>TIFF (Uncompressed)</PrimaryEncoding>				<ColorProfile>Adobe RGB (1998)</ColorProfile>			</MediaProperties>			<AnnotationFields>				<Headline>17</Headline>			</AnnotationFields>			<MetaDataFields>				<Maker>i2s Digibook Scanner</Maker>				<Model>Suprascan 10000 RGB</Model>				<Software>Digibook Version :5, 5, 8, 5</Software>				<SourceURL></SourceURL>			</MetaDataFields>		</MediaItem>		<MediaItem>			<AssetProperties>				<Filename>m000003027_0018.tif</Filename>				<Filepath>DSSR:scan:10_raw:m000003027:m000003027_0018.tif</Filepath>				<UniqueID>18</UniqueID>				<Label>0</Label>				<Rating>0</Rating>				<MediaType>TIFF</MediaType>				<FileSize unit="Bytes">180565830</FileSize>				<Created>2008:07:11 10:31:33</Created>				<Modified>2008:07:11 10:31:43</Modified>				<Added>2008:07:11 11:21:27</Added>				<Annotated>2008:07:11 14:15:25</Annotated>			<ThumbnailSource>Thumbnails_(m000003027):m000003027_0018.jpg</ThumbnailSource>			</AssetProperties>			<MediaProperties>				<Width unit="Pixels">6896</Width>				<Height unit="Pixels">8728</Height>				<Resolution unit="DPI">600</Resolution>				<Depth unit="Bits">24</Depth>				<ViewRotation>1</ViewRotation>				<SampleColor>R:B0 G:D0 B:90</SampleColor>				<Pages>1</Pages>				<ColorSpace>RGB </ColorSpace>				<Compression>65537</Compression>				<PrimaryEncoding>TIFF (Uncompressed)</PrimaryEncoding>				<ColorProfile>Adobe RGB (1998)</ColorProfile>			</MediaProperties>			<AnnotationFields>				<Headline>18</Headline>			</AnnotationFields>			<MetaDataFields>				<Maker>i2s Digibook Scanner</Maker>				<Model>Suprascan 10000 RGB</Model>				<Software>Digibook Version :5, 5, 8, 5</Software>				<SourceURL></SourceURL>			</MetaDataFields>		</MediaItem>		<MediaItem>			<AssetProperties>				<Filename>m000003027_0019.tif</Filename>				<Filepath>DSSR:scan:10_raw:m000003027:m000003027_0019.tif</Filepath>				<UniqueID>19</UniqueID>				<Label>0</Label>				<Rating>0</Rating>				<MediaType>TIFF</MediaType>				<FileSize unit="Bytes">176493510</FileSize>				<Created>2008:07:11 10:31:43</Created>				<Modified>2008:07:11 10:31:56</Modified>				<Added>2008:07:11 11:21:30</Added>				<Annotated>2008:07:11 14:15:28</Annotated>			<ThumbnailSource>Thumbnails_(m000003027):m000003027_0019.jpg</ThumbnailSource>			</AssetProperties>			<MediaProperties>				<Width unit="Pixels">6784</Width>				<Height unit="Pixels">8672</Height>				<Resolution unit="DPI">600</Resolution>				<Depth unit="Bits">24</Depth>				<ViewRotation>1</ViewRotation>				<SampleColor>R:B0 G:D0 B:90</SampleColor>				<Pages>1</Pages>				<ColorSpace>RGB </ColorSpace>				<Compression>65537</Compression>				<PrimaryEncoding>TIFF (Uncompressed)</PrimaryEncoding>				<ColorProfile>Adobe RGB (1998)</ColorProfile>			</MediaProperties>			<AnnotationFields>				<Headline>19</Headline>			</AnnotationFields>			<MetaDataFields>				<Maker>i2s Digibook Scanner</Maker>				<Model>Suprascan 10000 RGB</Model>				<Software>Digibook Version :5, 5, 8, 5</Software>				<SourceURL></SourceURL>			</MetaDataFields>		</MediaItem>		<MediaItem>			<AssetProperties>				<Filename>m000003027_0020.tif</Filename>				<Filepath>DSSR:scan:10_raw:m000003027:m000003027_0020.tif</Filepath>				<UniqueID>20</UniqueID>				<Label>0</Label>				<Rating>0</Rating>				<MediaType>TIFF</MediaType>				<FileSize unit="Bytes">176957382</FileSize>				<Created>2008:07:11 10:33:15</Created>				<Modified>2008:07:11 10:33:28</Modified>				<Added>2008:07:11 11:21:35</Added>				<Annotated>2008:07:11 14:15:34</Annotated>			<ThumbnailSource>Thumbnails_(m000003027):m000003027_0020.jpg</ThumbnailSource>			</AssetProperties>			<MediaProperties>				<Width unit="Pixels">6752</Width>				<Height unit="Pixels">8736</Height>				<Resolution unit="DPI">600</Resolution>				<Depth unit="Bits">24</Depth>				<ViewRotation>1</ViewRotation>				<SampleColor>R:B0 G:D0 B:90</SampleColor>				<Pages>1</Pages>				<ColorSpace>RGB </ColorSpace>				<Compression>65537</Compression>				<PrimaryEncoding>TIFF (Uncompressed)</PrimaryEncoding>				<ColorProfile>Adobe RGB (1998)</ColorProfile>			</MediaProperties>			<AnnotationFields>				<Headline>Back Page</Headline>			</AnnotationFields>			<MetaDataFields>				<Maker>i2s Digibook Scanner</Maker>				<Model>Suprascan 10000 RGB</Model>				<Software>Digibook Version :5, 5, 8, 5</Software>				<SourceURL></SourceURL>			</MetaDataFields>		</MediaItem>	</MediaItemList></CatalogType>