<?xml version="1.0" encoding="UTF-8"?>
<?expression media exportversion="1.0" appversion="1.0"?>
<CatalogType>
   <Catalog pathType="MAC">m000000938</Catalog>
   <MediaItemList>
      <MediaItem>
			      <AssetProperties>
				        <Filename>m000000938_0001.tif</Filename>
				        <Filepath>lib_content37:EAM_Sheet:m000000938:m000000938_0001.tif</Filepath>
				        <UniqueID>6185</UniqueID>
				        <Label>0</Label>
				        <Rating>0</Rating>
				        <MediaType>TIFF</MediaType>
				        <FileSize unit="Bytes">174289932</FileSize>
				        <Created>2011:01:26 23:41:20</Created>
				        <Modified>2011:01:26 23:43:55</Modified>
				        <Added>2011:01:31 10:28:04</Added>
				        <Annotated>2011:02:02 16:55:06</Annotated>
			      </AssetProperties>
			      <MediaProperties>
				        <Width unit="Pixels">6768</Width>
				        <Height unit="Pixels">8584</Height>
				        <Resolution unit="DPI">600</Resolution>
				        <Depth unit="Bits">24</Depth>
				        <ViewRotation>1</ViewRotation>
				        <SampleColor>R:C0 G:D0 B:A0</SampleColor>
				        <Pages>1</Pages>
				        <ColorSpace>RGB </ColorSpace>
				        <Compression>65537</Compression>
				        <PrimaryEncoding>TIFF (Uncompressed)</PrimaryEncoding>
				        <ColorProfile/>
			      </MediaProperties>
			      <AnnotationFields>
				        <Headline>1</Headline>
			      </AnnotationFields>
			      <MetaDataFields>
				        <Maker>i2s Digibook Scanner</Maker>
				        <Model>Suprascan 10000 RGB</Model>
				        <Software>Digibook Version :5, 5, 0, 23</Software>
				        <SourceURL/>
			      </MetaDataFields>
		    </MediaItem>
      <MediaItem>
			      <AssetProperties>
				        <Filename>m000000938_0002.tif</Filename>
				        <Filepath>lib_content37:EAM_Sheet:m000000938:m000000938_0002.tif</Filepath>
				        <UniqueID>6186</UniqueID>
				        <Label>0</Label>
				        <Rating>0</Rating>
				        <MediaType>TIFF</MediaType>
				        <FileSize unit="Bytes">172538892</FileSize>
				        <Created>2011:01:26 23:43:55</Created>
				        <Modified>2011:01:26 23:46:06</Modified>
				        <Added>2011:01:31 10:28:04</Added>
				        <Annotated>2011:02:02 16:55:06</Annotated>
			      </AssetProperties>
			      <MediaProperties>
				        <Width unit="Pixels">6744</Width>
				        <Height unit="Pixels">8528</Height>
				        <Resolution unit="DPI">600</Resolution>
				        <Depth unit="Bits">24</Depth>
				        <ViewRotation>1</ViewRotation>
				        <SampleColor>R:C0 G:D0 B:A0</SampleColor>
				        <Pages>1</Pages>
				        <ColorSpace>RGB </ColorSpace>
				        <Compression>65537</Compression>
				        <PrimaryEncoding>TIFF (Uncompressed)</PrimaryEncoding>
				        <ColorProfile/>
			      </MediaProperties>
			      <AnnotationFields>
				        <Headline>2</Headline>
			      </AnnotationFields>
			      <MetaDataFields>
				        <Maker>i2s Digibook Scanner</Maker>
				        <Model>Suprascan 10000 RGB</Model>
				        <Software>Digibook Version :5, 5, 0, 23</Software>
				        <SourceURL/>
			      </MetaDataFields>
		    </MediaItem>
      <MediaItem>
			      <AssetProperties>
				        <Filename>m000000938_0003.tif</Filename>
				        <Filepath>lib_content37:EAM_Sheet:m000000938:m000000938_0003.tif</Filepath>
				        <UniqueID>6187</UniqueID>
				        <Label>0</Label>
				        <Rating>0</Rating>
				        <MediaType>TIFF</MediaType>
				        <FileSize unit="Bytes">172625868</FileSize>
				        <Created>2011:01:26 23:46:06</Created>
				        <Modified>2011:01:26 23:46:36</Modified>
				        <Added>2011:01:31 10:28:04</Added>
				        <Annotated>2011:02:02 16:55:07</Annotated>
			      </AssetProperties>
			      <MediaProperties>
				        <Width unit="Pixels">6792</Width>
				        <Height unit="Pixels">8472</Height>
				        <Resolution unit="DPI">600</Resolution>
				        <Depth unit="Bits">24</Depth>
				        <ViewRotation>1</ViewRotation>
				        <SampleColor>R:C0 G:D0 B:A0</SampleColor>
				        <Pages>1</Pages>
				        <ColorSpace>RGB </ColorSpace>
				        <Compression>65537</Compression>
				        <PrimaryEncoding>TIFF (Uncompressed)</PrimaryEncoding>
				        <ColorProfile/>
			      </MediaProperties>
			      <AnnotationFields>
				        <Headline>3</Headline>
			      </AnnotationFields>
			      <MetaDataFields>
				        <Maker>i2s Digibook Scanner</Maker>
				        <Model>Suprascan 10000 RGB</Model>
				        <Software>Digibook Version :5, 5, 0, 23</Software>
				        <SourceURL/>
			      </MetaDataFields>
		    </MediaItem>
      <MediaItem>
			      <AssetProperties>
				        <Filename>m000000938_0004.tif</Filename>
				        <Filepath>lib_content37:EAM_Sheet:m000000938:m000000938_0004.tif</Filepath>
				        <UniqueID>6188</UniqueID>
				        <Label>0</Label>
				        <Rating>0</Rating>
				        <MediaType>TIFF</MediaType>
				        <FileSize unit="Bytes">175277196</FileSize>
				        <Created>2011:01:26 23:48:08</Created>
				        <Modified>2011:01:26 23:48:18</Modified>
				        <Added>2011:01:31 10:28:04</Added>
				        <Annotated>2011:02:02 16:55:07</Annotated>
			      </AssetProperties>
			      <MediaProperties>
				        <Width unit="Pixels">6800</Width>
				        <Height unit="Pixels">8592</Height>
				        <Resolution unit="DPI">600</Resolution>
				        <Depth unit="Bits">24</Depth>
				        <ViewRotation>1</ViewRotation>
				        <SampleColor>R:C0 G:D0 B:90</SampleColor>
				        <Pages>1</Pages>
				        <ColorSpace>RGB </ColorSpace>
				        <Compression>65537</Compression>
				        <PrimaryEncoding>TIFF (Uncompressed)</PrimaryEncoding>
				        <ColorProfile/>
			      </MediaProperties>
			      <AnnotationFields>
				        <Headline>Back Cover</Headline>
			      </AnnotationFields>
			      <MetaDataFields>
				        <Maker>i2s Digibook Scanner</Maker>
				        <Model>Suprascan 10000 RGB</Model>
				        <Software>Digibook Version :5, 5, 0, 23</Software>
				        <SourceURL/>
			      </MetaDataFields>
		    </MediaItem>
   </MediaItemList>
</CatalogType>