<?xml version="1.0" encoding="UTF-8"?>
<?expression media exportversion="1.0" appversion="1.0"?>
<CatalogType>
   <Catalog pathType="MAC">m000000095</Catalog>
   <MediaItemList>
      <MediaItem>
			      <AssetProperties>
				        <Filename>m000000095_0001.tif</Filename>
				        <Filepath>lib_content37:EAM_Sheet:m000000095:m000000095_0001.tif</Filepath>
				        <UniqueID>691</UniqueID>
				        <Label>0</Label>
				        <Rating>0</Rating>
				        <MediaType>TIFF</MediaType>
				        <FileSize unit="Bytes">181359756</FileSize>
				        <Created>2011:01:25 16:09:23</Created>
				        <Modified>2011:01:25 16:15:01</Modified>
				        <Added>2011:01:31 10:26:45</Added>
				        <Annotated>2011:02:02 13:53:07</Annotated>
			      </AssetProperties>
			      <MediaProperties>
				        <Width unit="Pixels">6920</Width>
				        <Height unit="Pixels">8736</Height>
				        <Resolution unit="DPI">600</Resolution>
				        <Depth unit="Bits">24</Depth>
				        <ViewRotation>1</ViewRotation>
				        <SampleColor>R:A0 G:C0 B:80</SampleColor>
				        <Pages>1</Pages>
				        <ColorSpace>RGB </ColorSpace>
				        <Compression>65537</Compression>
				        <PrimaryEncoding>TIFF (Uncompressed)</PrimaryEncoding>
				        <ColorProfile/>
			      </MediaProperties>
			      <AnnotationFields>
				        <Headline>Front Cover</Headline>
			      </AnnotationFields>
			      <MetaDataFields>
				        <Maker>i2s Digibook Scanner</Maker>
				        <Model>Suprascan 10000 RGB</Model>
				        <Software>Digibook Version :5, 5, 0, 23</Software>
				        <SourceURL/>
			      </MetaDataFields>
		    </MediaItem>
      <MediaItem>
			      <AssetProperties>
				        <Filename>m000000095_0002.tif</Filename>
				        <Filepath>lib_content37:EAM_Sheet:m000000095:m000000095_0002.tif</Filepath>
				        <UniqueID>692</UniqueID>
				        <Label>0</Label>
				        <Rating>0</Rating>
				        <MediaType>TIFF</MediaType>
				        <FileSize unit="Bytes">178788492</FileSize>
				        <Created>2011:01:25 16:15:01</Created>
				        <Modified>2011:01:25 16:19:30</Modified>
				        <Added>2011:01:31 10:26:45</Added>
				        <Annotated>2011:02:02 13:53:08</Annotated>
			      </AssetProperties>
			      <MediaProperties>
				        <Width unit="Pixels">7008</Width>
				        <Height unit="Pixels">8504</Height>
				        <Resolution unit="DPI">600</Resolution>
				        <Depth unit="Bits">24</Depth>
				        <ViewRotation>1</ViewRotation>
				        <SampleColor>R:C0 G:D0 B:A0</SampleColor>
				        <Pages>1</Pages>
				        <ColorSpace>RGB </ColorSpace>
				        <Compression>65537</Compression>
				        <PrimaryEncoding>TIFF (Uncompressed)</PrimaryEncoding>
				        <ColorProfile/>
			      </MediaProperties>
			      <AnnotationFields>
				        <Headline>2</Headline>
			      </AnnotationFields>
			      <MetaDataFields>
				        <Maker>i2s Digibook Scanner</Maker>
				        <Model>Suprascan 10000 RGB</Model>
				        <Software>Digibook Version :5, 5, 0, 23</Software>
				        <SourceURL/>
			      </MetaDataFields>
		    </MediaItem>
      <MediaItem>
			      <AssetProperties>
				        <Filename>m000000095_0003.tif</Filename>
				        <Filepath>lib_content37:EAM_Sheet:m000000095:m000000095_0003.tif</Filepath>
				        <UniqueID>693</UniqueID>
				        <Label>0</Label>
				        <Rating>0</Rating>
				        <MediaType>TIFF</MediaType>
				        <FileSize unit="Bytes">180197196</FileSize>
				        <Created>2011:01:25 16:19:30</Created>
				        <Modified>2011:01:25 16:26:35</Modified>
				        <Added>2011:01:31 10:26:45</Added>
				        <Annotated>2011:02:02 13:53:08</Annotated>
			      </AssetProperties>
			      <MediaProperties>
				        <Width unit="Pixels">6920</Width>
				        <Height unit="Pixels">8680</Height>
				        <Resolution unit="DPI">600</Resolution>
				        <Depth unit="Bits">24</Depth>
				        <ViewRotation>1</ViewRotation>
				        <SampleColor>R:C0 G:D0 B:A0</SampleColor>
				        <Pages>1</Pages>
				        <ColorSpace>RGB </ColorSpace>
				        <Compression>65537</Compression>
				        <PrimaryEncoding>TIFF (Uncompressed)</PrimaryEncoding>
				        <ColorProfile/>
			      </MediaProperties>
			      <AnnotationFields>
				        <Headline>3</Headline>
			      </AnnotationFields>
			      <MetaDataFields>
				        <Maker>i2s Digibook Scanner</Maker>
				        <Model>Suprascan 10000 RGB</Model>
				        <Software>Digibook Version :5, 5, 0, 23</Software>
				        <SourceURL/>
			      </MetaDataFields>
		    </MediaItem>
      <MediaItem>
			      <AssetProperties>
				        <Filename>m000000095_0004.tif</Filename>
				        <Filepath>lib_content37:EAM_Sheet:m000000095:m000000095_0004.tif</Filepath>
				        <UniqueID>694</UniqueID>
				        <Label>0</Label>
				        <Rating>0</Rating>
				        <MediaType>TIFF</MediaType>
				        <FileSize unit="Bytes">178486668</FileSize>
				        <Created>2011:01:25 16:26:35</Created>
				        <Modified>2011:01:25 16:31:41</Modified>
				        <Added>2011:01:31 10:26:45</Added>
				        <Annotated>2011:02:02 13:53:09</Annotated>
			      </AssetProperties>
			      <MediaProperties>
				        <Width unit="Pixels">6848</Width>
				        <Height unit="Pixels">8688</Height>
				        <Resolution unit="DPI">600</Resolution>
				        <Depth unit="Bits">24</Depth>
				        <ViewRotation>1</ViewRotation>
				        <SampleColor>R:B0 G:C0 B:90</SampleColor>
				        <Pages>1</Pages>
				        <ColorSpace>RGB </ColorSpace>
				        <Compression>65537</Compression>
				        <PrimaryEncoding>TIFF (Uncompressed)</PrimaryEncoding>
				        <ColorProfile/>
			      </MediaProperties>
			      <AnnotationFields>
				        <Headline>4</Headline>
			      </AnnotationFields>
			      <MetaDataFields>
				        <Maker>i2s Digibook Scanner</Maker>
				        <Model>Suprascan 10000 RGB</Model>
				        <Software>Digibook Version :5, 5, 0, 23</Software>
				        <SourceURL/>
			      </MetaDataFields>
		    </MediaItem>
      <MediaItem>
			      <AssetProperties>
				        <Filename>m000000095_0005.tif</Filename>
				        <Filepath>lib_content37:EAM_Sheet:m000000095:m000000095_0005.tif</Filepath>
				        <UniqueID>695</UniqueID>
				        <Label>0</Label>
				        <Rating>0</Rating>
				        <MediaType>TIFF</MediaType>
				        <FileSize unit="Bytes">180197196</FileSize>
				        <Created>2011:01:25 16:31:41</Created>
				        <Modified>2011:01:25 16:32:53</Modified>
				        <Added>2011:01:31 10:26:45</Added>
				        <Annotated>2011:02:02 13:53:09</Annotated>
			      </AssetProperties>
			      <MediaProperties>
				        <Width unit="Pixels">6920</Width>
				        <Height unit="Pixels">8680</Height>
				        <Resolution unit="DPI">600</Resolution>
				        <Depth unit="Bits">24</Depth>
				        <ViewRotation>1</ViewRotation>
				        <SampleColor>R:C0 G:D0 B:A0</SampleColor>
				        <Pages>1</Pages>
				        <ColorSpace>RGB </ColorSpace>
				        <Compression>65537</Compression>
				        <PrimaryEncoding>TIFF (Uncompressed)</PrimaryEncoding>
				        <ColorProfile/>
			      </MediaProperties>
			      <AnnotationFields>
				        <Headline>5</Headline>
			      </AnnotationFields>
			      <MetaDataFields>
				        <Maker>i2s Digibook Scanner</Maker>
				        <Model>Suprascan 10000 RGB</Model>
				        <Software>Digibook Version :5, 5, 0, 23</Software>
				        <SourceURL/>
			      </MetaDataFields>
		    </MediaItem>
      <MediaItem>
			      <AssetProperties>
				        <Filename>m000000095_0006.tif</Filename>
				        <Filepath>lib_content37:EAM_Sheet:m000000095:m000000095_0006.tif</Filepath>
				        <UniqueID>696</UniqueID>
				        <Label>0</Label>
				        <Rating>0</Rating>
				        <MediaType>TIFF</MediaType>
				        <FileSize unit="Bytes">179112204</FileSize>
				        <Created>2011:01:25 16:36:51</Created>
				        <Modified>2011:01:25 16:40:46</Modified>
				        <Added>2011:01:31 10:26:45</Added>
				        <Annotated>2011:02:02 13:53:09</Annotated>
			      </AssetProperties>
			      <MediaProperties>
				        <Width unit="Pixels">6872</Width>
				        <Height unit="Pixels">8688</Height>
				        <Resolution unit="DPI">600</Resolution>
				        <Depth unit="Bits">24</Depth>
				        <ViewRotation>1</ViewRotation>
				        <SampleColor>R:C0 G:D0 B:A0</SampleColor>
				        <Pages>1</Pages>
				        <ColorSpace>RGB </ColorSpace>
				        <Compression>65537</Compression>
				        <PrimaryEncoding>TIFF (Uncompressed)</PrimaryEncoding>
				        <ColorProfile/>
			      </MediaProperties>
			      <AnnotationFields>
				        <Headline>6</Headline>
			      </AnnotationFields>
			      <MetaDataFields>
				        <Maker>i2s Digibook Scanner</Maker>
				        <Model>Suprascan 10000 RGB</Model>
				        <Software>Digibook Version :5, 5, 0, 23</Software>
				        <SourceURL/>
			      </MetaDataFields>
		    </MediaItem>
      <MediaItem>
			      <AssetProperties>
				        <Filename>m000000095_0007.tif</Filename>
				        <Filepath>lib_content37:EAM_Sheet:m000000095:m000000095_0007.tif</Filepath>
				        <UniqueID>697</UniqueID>
				        <Label>0</Label>
				        <Rating>0</Rating>
				        <MediaType>TIFF</MediaType>
				        <FileSize unit="Bytes">181238796</FileSize>
				        <Created>2011:01:25 16:40:46</Created>
				        <Modified>2011:01:25 16:44:26</Modified>
				        <Added>2011:01:31 10:26:45</Added>
				        <Annotated>2011:02:02 13:53:10</Annotated>
			      </AssetProperties>
			      <MediaProperties>
				        <Width unit="Pixels">6960</Width>
				        <Height unit="Pixels">8680</Height>
				        <Resolution unit="DPI">600</Resolution>
				        <Depth unit="Bits">24</Depth>
				        <ViewRotation>1</ViewRotation>
				        <SampleColor>R:C0 G:D0 B:A0</SampleColor>
				        <Pages>1</Pages>
				        <ColorSpace>RGB </ColorSpace>
				        <Compression>65537</Compression>
				        <PrimaryEncoding>TIFF (Uncompressed)</PrimaryEncoding>
				        <ColorProfile/>
			      </MediaProperties>
			      <AnnotationFields>
				        <Headline>7</Headline>
			      </AnnotationFields>
			      <MetaDataFields>
				        <Maker>i2s Digibook Scanner</Maker>
				        <Model>Suprascan 10000 RGB</Model>
				        <Software>Digibook Version :5, 5, 0, 23</Software>
				        <SourceURL/>
			      </MetaDataFields>
		    </MediaItem>
      <MediaItem>
			      <AssetProperties>
				        <Filename>m000000095_0008.tif</Filename>
				        <Filepath>lib_content37:EAM_Sheet:m000000095:m000000095_0008.tif</Filepath>
				        <UniqueID>698</UniqueID>
				        <Label>0</Label>
				        <Rating>0</Rating>
				        <MediaType>TIFF</MediaType>
				        <FileSize unit="Bytes">178903692</FileSize>
				        <Created>2011:01:25 16:44:26</Created>
				        <Modified>2011:01:25 16:47:06</Modified>
				        <Added>2011:01:31 10:26:45</Added>
				        <Annotated>2011:02:02 13:53:11</Annotated>
			      </AssetProperties>
			      <MediaProperties>
				        <Width unit="Pixels">6864</Width>
				        <Height unit="Pixels">8688</Height>
				        <Resolution unit="DPI">600</Resolution>
				        <Depth unit="Bits">24</Depth>
				        <ViewRotation>1</ViewRotation>
				        <SampleColor>R:C0 G:D0 B:A0</SampleColor>
				        <Pages>1</Pages>
				        <ColorSpace>RGB </ColorSpace>
				        <Compression>65537</Compression>
				        <PrimaryEncoding>TIFF (Uncompressed)</PrimaryEncoding>
				        <ColorProfile/>
			      </MediaProperties>
			      <AnnotationFields>
				        <Headline>8</Headline>
			      </AnnotationFields>
			      <MetaDataFields>
				        <Maker>i2s Digibook Scanner</Maker>
				        <Model>Suprascan 10000 RGB</Model>
				        <Software>Digibook Version :5, 5, 0, 23</Software>
				        <SourceURL/>
			      </MetaDataFields>
		    </MediaItem>
      <MediaItem>
			      <AssetProperties>
				        <Filename>m000000095_0009.tif</Filename>
				        <Filepath>lib_content37:EAM_Sheet:m000000095:m000000095_0009.tif</Filepath>
				        <UniqueID>699</UniqueID>
				        <Label>0</Label>
				        <Rating>0</Rating>
				        <MediaType>TIFF</MediaType>
				        <FileSize unit="Bytes">181238796</FileSize>
				        <Created>2011:01:25 16:47:06</Created>
				        <Modified>2011:01:25 16:48:49</Modified>
				        <Added>2011:01:31 10:26:45</Added>
				        <Annotated>2011:02:02 13:53:11</Annotated>
			      </AssetProperties>
			      <MediaProperties>
				        <Width unit="Pixels">6960</Width>
				        <Height unit="Pixels">8680</Height>
				        <Resolution unit="DPI">600</Resolution>
				        <Depth unit="Bits">24</Depth>
				        <ViewRotation>1</ViewRotation>
				        <SampleColor>R:C0 G:D0 B:A0</SampleColor>
				        <Pages>1</Pages>
				        <ColorSpace>RGB </ColorSpace>
				        <Compression>65537</Compression>
				        <PrimaryEncoding>TIFF (Uncompressed)</PrimaryEncoding>
				        <ColorProfile/>
			      </MediaProperties>
			      <AnnotationFields>
				        <Headline>9</Headline>
			      </AnnotationFields>
			      <MetaDataFields>
				        <Maker>i2s Digibook Scanner</Maker>
				        <Model>Suprascan 10000 RGB</Model>
				        <Software>Digibook Version :5, 5, 0, 23</Software>
				        <SourceURL/>
			      </MetaDataFields>
		    </MediaItem>
      <MediaItem>
			      <AssetProperties>
				        <Filename>m000000095_0010.tif</Filename>
				        <Filepath>lib_content37:EAM_Sheet:m000000095:m000000095_0010.tif</Filepath>
				        <UniqueID>700</UniqueID>
				        <Label>0</Label>
				        <Rating>0</Rating>
				        <MediaType>TIFF</MediaType>
				        <FileSize unit="Bytes">178903692</FileSize>
				        <Created>2011:01:25 16:48:49</Created>
				        <Modified>2011:01:25 16:50:31</Modified>
				        <Added>2011:01:31 10:26:45</Added>
				        <Annotated>2011:02:02 13:53:12</Annotated>
			      </AssetProperties>
			      <MediaProperties>
				        <Width unit="Pixels">6864</Width>
				        <Height unit="Pixels">8688</Height>
				        <Resolution unit="DPI">600</Resolution>
				        <Depth unit="Bits">24</Depth>
				        <ViewRotation>1</ViewRotation>
				        <SampleColor>R:C0 G:D0 B:A0</SampleColor>
				        <Pages>1</Pages>
				        <ColorSpace>RGB </ColorSpace>
				        <Compression>65537</Compression>
				        <PrimaryEncoding>TIFF (Uncompressed)</PrimaryEncoding>
				        <ColorProfile/>
			      </MediaProperties>
			      <AnnotationFields>
				        <Headline>10</Headline>
			      </AnnotationFields>
			      <MetaDataFields>
				        <Maker>i2s Digibook Scanner</Maker>
				        <Model>Suprascan 10000 RGB</Model>
				        <Software>Digibook Version :5, 5, 0, 23</Software>
				        <SourceURL/>
			      </MetaDataFields>
		    </MediaItem>
      <MediaItem>
			      <AssetProperties>
				        <Filename>m000000095_0011.tif</Filename>
				        <Filepath>lib_content37:EAM_Sheet:m000000095:m000000095_0011.tif</Filepath>
				        <UniqueID>701</UniqueID>
				        <Label>0</Label>
				        <Rating>0</Rating>
				        <MediaType>TIFF</MediaType>
				        <FileSize unit="Bytes">181238796</FileSize>
				        <Created>2011:01:25 16:50:31</Created>
				        <Modified>2011:01:25 16:52:02</Modified>
				        <Added>2011:01:31 10:26:45</Added>
				        <Annotated>2011:02:02 13:53:13</Annotated>
			      </AssetProperties>
			      <MediaProperties>
				        <Width unit="Pixels">6960</Width>
				        <Height unit="Pixels">8680</Height>
				        <Resolution unit="DPI">600</Resolution>
				        <Depth unit="Bits">24</Depth>
				        <ViewRotation>1</ViewRotation>
				        <SampleColor>R:C0 G:D0 B:A0</SampleColor>
				        <Pages>1</Pages>
				        <ColorSpace>RGB </ColorSpace>
				        <Compression>65537</Compression>
				        <PrimaryEncoding>TIFF (Uncompressed)</PrimaryEncoding>
				        <ColorProfile/>
			      </MediaProperties>
			      <AnnotationFields>
				        <Headline>11</Headline>
			      </AnnotationFields>
			      <MetaDataFields>
				        <Maker>i2s Digibook Scanner</Maker>
				        <Model>Suprascan 10000 RGB</Model>
				        <Software>Digibook Version :5, 5, 0, 23</Software>
				        <SourceURL/>
			      </MetaDataFields>
		    </MediaItem>
      <MediaItem>
			      <AssetProperties>
				        <Filename>m000000095_0012.tif</Filename>
				        <Filepath>lib_content37:EAM_Sheet:m000000095:m000000095_0012.tif</Filepath>
				        <UniqueID>702</UniqueID>
				        <Label>0</Label>
				        <Rating>0</Rating>
				        <MediaType>TIFF</MediaType>
				        <FileSize unit="Bytes">181405836</FileSize>
				        <Created>2011:01:25 16:52:02</Created>
				        <Modified>2011:01:25 16:52:17</Modified>
				        <Added>2011:01:31 10:26:45</Added>
				        <Annotated>2011:02:02 13:53:13</Annotated>
			      </AssetProperties>
			      <MediaProperties>
				        <Width unit="Pixels">6960</Width>
				        <Height unit="Pixels">8688</Height>
				        <Resolution unit="DPI">600</Resolution>
				        <Depth unit="Bits">24</Depth>
				        <ViewRotation>1</ViewRotation>
				        <SampleColor>R:C0 G:D0 B:A0</SampleColor>
				        <Pages>1</Pages>
				        <ColorSpace>RGB </ColorSpace>
				        <Compression>65537</Compression>
				        <PrimaryEncoding>TIFF (Uncompressed)</PrimaryEncoding>
				        <ColorProfile/>
			      </MediaProperties>
			      <AnnotationFields>
				        <Headline>12</Headline>
			      </AnnotationFields>
			      <MetaDataFields>
				        <Maker>i2s Digibook Scanner</Maker>
				        <Model>Suprascan 10000 RGB</Model>
				        <Software>Digibook Version :5, 5, 0, 23</Software>
				        <SourceURL/>
			      </MetaDataFields>
		    </MediaItem>
      <MediaItem>
			      <AssetProperties>
				        <Filename>m000000095_0013.tif</Filename>
				        <Filepath>lib_content37:EAM_Sheet:m000000095:m000000095_0013.tif</Filepath>
				        <UniqueID>703</UniqueID>
				        <Label>0</Label>
				        <Rating>0</Rating>
				        <MediaType>TIFF</MediaType>
				        <FileSize unit="Bytes">181238796</FileSize>
				        <Created>2011:01:25 16:52:17</Created>
				        <Modified>2011:01:25 16:52:33</Modified>
				        <Added>2011:01:31 10:26:45</Added>
				        <Annotated>2011:02:02 13:53:14</Annotated>
			      </AssetProperties>
			      <MediaProperties>
				        <Width unit="Pixels">6960</Width>
				        <Height unit="Pixels">8680</Height>
				        <Resolution unit="DPI">600</Resolution>
				        <Depth unit="Bits">24</Depth>
				        <ViewRotation>1</ViewRotation>
				        <SampleColor>R:C0 G:D0 B:A0</SampleColor>
				        <Pages>1</Pages>
				        <ColorSpace>RGB </ColorSpace>
				        <Compression>65537</Compression>
				        <PrimaryEncoding>TIFF (Uncompressed)</PrimaryEncoding>
				        <ColorProfile/>
			      </MediaProperties>
			      <AnnotationFields>
				        <Headline>13</Headline>
			      </AnnotationFields>
			      <MetaDataFields>
				        <Maker>i2s Digibook Scanner</Maker>
				        <Model>Suprascan 10000 RGB</Model>
				        <Software>Digibook Version :5, 5, 0, 23</Software>
				        <SourceURL/>
			      </MetaDataFields>
		    </MediaItem>
      <MediaItem>
			      <AssetProperties>
				        <Filename>m000000095_0014.tif</Filename>
				        <Filepath>lib_content37:EAM_Sheet:m000000095:m000000095_0014.tif</Filepath>
				        <UniqueID>704</UniqueID>
				        <Label>0</Label>
				        <Rating>0</Rating>
				        <MediaType>TIFF</MediaType>
				        <FileSize unit="Bytes">181405836</FileSize>
				        <Created>2011:01:25 16:52:33</Created>
				        <Modified>2011:01:25 16:52:48</Modified>
				        <Added>2011:01:31 10:26:45</Added>
				        <Annotated>2011:02:02 13:53:15</Annotated>
			      </AssetProperties>
			      <MediaProperties>
				        <Width unit="Pixels">6960</Width>
				        <Height unit="Pixels">8688</Height>
				        <Resolution unit="DPI">600</Resolution>
				        <Depth unit="Bits">24</Depth>
				        <ViewRotation>1</ViewRotation>
				        <SampleColor>R:C0 G:D0 B:A0</SampleColor>
				        <Pages>1</Pages>
				        <ColorSpace>RGB </ColorSpace>
				        <Compression>65537</Compression>
				        <PrimaryEncoding>TIFF (Uncompressed)</PrimaryEncoding>
				        <ColorProfile/>
			      </MediaProperties>
			      <AnnotationFields>
				        <Headline>14</Headline>
			      </AnnotationFields>
			      <MetaDataFields>
				        <Maker>i2s Digibook Scanner</Maker>
				        <Model>Suprascan 10000 RGB</Model>
				        <Software>Digibook Version :5, 5, 0, 23</Software>
				        <SourceURL/>
			      </MetaDataFields>
		    </MediaItem>
      <MediaItem>
			      <AssetProperties>
				        <Filename>m000000095_0015.tif</Filename>
				        <Filepath>lib_content37:EAM_Sheet:m000000095:m000000095_0015.tif</Filepath>
				        <UniqueID>705</UniqueID>
				        <Label>0</Label>
				        <Rating>0</Rating>
				        <MediaType>TIFF</MediaType>
				        <FileSize unit="Bytes">181238796</FileSize>
				        <Created>2011:01:25 16:52:48</Created>
				        <Modified>2011:01:25 16:53:02</Modified>
				        <Added>2011:01:31 10:26:45</Added>
				        <Annotated>2011:02:02 13:53:15</Annotated>
			      </AssetProperties>
			      <MediaProperties>
				        <Width unit="Pixels">6960</Width>
				        <Height unit="Pixels">8680</Height>
				        <Resolution unit="DPI">600</Resolution>
				        <Depth unit="Bits">24</Depth>
				        <ViewRotation>1</ViewRotation>
				        <SampleColor>R:B0 G:C0 B:90</SampleColor>
				        <Pages>1</Pages>
				        <ColorSpace>RGB </ColorSpace>
				        <Compression>65537</Compression>
				        <PrimaryEncoding>TIFF (Uncompressed)</PrimaryEncoding>
				        <ColorProfile/>
			      </MediaProperties>
			      <AnnotationFields>
				        <Headline>15</Headline>
			      </AnnotationFields>
			      <MetaDataFields>
				        <Maker>i2s Digibook Scanner</Maker>
				        <Model>Suprascan 10000 RGB</Model>
				        <Software>Digibook Version :5, 5, 0, 23</Software>
				        <SourceURL/>
			      </MetaDataFields>
		    </MediaItem>
      <MediaItem>
			      <AssetProperties>
				        <Filename>m000000095_0016.tif</Filename>
				        <Filepath>lib_content37:EAM_Sheet:m000000095:m000000095_0016.tif</Filepath>
				        <UniqueID>706</UniqueID>
				        <Label>0</Label>
				        <Rating>0</Rating>
				        <MediaType>TIFF</MediaType>
				        <FileSize unit="Bytes">185576076</FileSize>
				        <Created>2011:01:25 16:53:02</Created>
				        <Modified>2011:01:25 16:53:18</Modified>
				        <Added>2011:01:31 10:26:45</Added>
				        <Annotated>2011:02:02 13:53:17</Annotated>
			      </AssetProperties>
			      <MediaProperties>
				        <Width unit="Pixels">7120</Width>
				        <Height unit="Pixels">8688</Height>
				        <Resolution unit="DPI">600</Resolution>
				        <Depth unit="Bits">24</Depth>
				        <ViewRotation>1</ViewRotation>
				        <SampleColor>R:B0 G:C0 B:90</SampleColor>
				        <Pages>1</Pages>
				        <ColorSpace>RGB </ColorSpace>
				        <Compression>65537</Compression>
				        <PrimaryEncoding>TIFF (Uncompressed)</PrimaryEncoding>
				        <ColorProfile/>
			      </MediaProperties>
			      <AnnotationFields>
				        <Headline>16</Headline>
			      </AnnotationFields>
			      <MetaDataFields>
				        <Maker>i2s Digibook Scanner</Maker>
				        <Model>Suprascan 10000 RGB</Model>
				        <Software>Digibook Version :5, 5, 0, 23</Software>
				        <SourceURL/>
			      </MetaDataFields>
		    </MediaItem>
      <MediaItem>
			      <AssetProperties>
				        <Filename>m000000095_0017.tif</Filename>
				        <Filepath>lib_content37:EAM_Sheet:m000000095:m000000095_0017.tif</Filepath>
				        <UniqueID>707</UniqueID>
				        <Label>0</Label>
				        <Rating>0</Rating>
				        <MediaType>TIFF</MediaType>
				        <FileSize unit="Bytes">176447436</FileSize>
				        <Created>2011:01:25 16:53:18</Created>
				        <Modified>2011:01:25 16:53:28</Modified>
				        <Added>2011:01:31 10:26:45</Added>
				        <Annotated>2011:02:02 13:53:17</Annotated>
			      </AssetProperties>
			      <MediaProperties>
				        <Width unit="Pixels">6776</Width>
				        <Height unit="Pixels">8680</Height>
				        <Resolution unit="DPI">600</Resolution>
				        <Depth unit="Bits">24</Depth>
				        <ViewRotation>1</ViewRotation>
				        <SampleColor>R:B0 G:C0 B:90</SampleColor>
				        <Pages>1</Pages>
				        <ColorSpace>RGB </ColorSpace>
				        <Compression>65537</Compression>
				        <PrimaryEncoding>TIFF (Uncompressed)</PrimaryEncoding>
				        <ColorProfile/>
			      </MediaProperties>
			      <AnnotationFields>
				        <Headline>17</Headline>
			      </AnnotationFields>
			      <MetaDataFields>
				        <Maker>i2s Digibook Scanner</Maker>
				        <Model>Suprascan 10000 RGB</Model>
				        <Software>Digibook Version :5, 5, 0, 23</Software>
				        <SourceURL/>
			      </MetaDataFields>
		    </MediaItem>
      <MediaItem>
			      <AssetProperties>
				        <Filename>m000000095_0018.tif</Filename>
				        <Filepath>lib_content37:EAM_Sheet:m000000095:m000000095_0018.tif</Filepath>
				        <UniqueID>708</UniqueID>
				        <Label>0</Label>
				        <Rating>0</Rating>
				        <MediaType>TIFF</MediaType>
				        <FileSize unit="Bytes">180363276</FileSize>
				        <Created>2011:01:25 16:53:28</Created>
				        <Modified>2011:01:25 16:53:38</Modified>
				        <Added>2011:01:31 10:26:45</Added>
				        <Annotated>2011:02:02 13:53:20</Annotated>
			      </AssetProperties>
			      <MediaProperties>
				        <Width unit="Pixels">6920</Width>
				        <Height unit="Pixels">8688</Height>
				        <Resolution unit="DPI">600</Resolution>
				        <Depth unit="Bits">24</Depth>
				        <ViewRotation>1</ViewRotation>
				        <SampleColor>R:A0 G:B0 B:80</SampleColor>
				        <Pages>1</Pages>
				        <ColorSpace>RGB </ColorSpace>
				        <Compression>65537</Compression>
				        <PrimaryEncoding>TIFF (Uncompressed)</PrimaryEncoding>
				        <ColorProfile/>
			      </MediaProperties>
			      <AnnotationFields>
				        <Headline>Back Cover</Headline>
			      </AnnotationFields>
			      <MetaDataFields>
				        <Maker>i2s Digibook Scanner</Maker>
				        <Model>Suprascan 10000 RGB</Model>
				        <Software>Digibook Version :5, 5, 0, 23</Software>
				        <SourceURL/>
			      </MetaDataFields>
		    </MediaItem>
   </MediaItemList>
</CatalogType>