<?xml version="1.0" encoding="UTF-8"?>
<?expression media exportversion="1.0" appversion="1.0"?>
<CatalogType>
   <Catalog pathType="MAC">m000000779</Catalog>
   <MediaItemList>
      <MediaItem>
			      <AssetProperties>
				        <Filename>m000000779_0001.tif</Filename>
				        <Filepath>lib_content37:EAM_Sheet:m000000779:m000000779_0001.tif</Filepath>
				        <UniqueID>5273</UniqueID>
				        <Label>0</Label>
				        <Rating>0</Rating>
				        <MediaType>TIFF</MediaType>
				        <FileSize unit="Bytes">177929097</FileSize>
				        <Created>2011:01:26 18:37:19</Created>
				        <Modified>2011:01:26 18:40:47</Modified>
				        <Added>2011:01:31 10:27:44</Added>
				        <Annotated>2011:02:02 16:08:35</Annotated>
			      </AssetProperties>
			      <MediaProperties>
				        <Width unit="Pixels">6752</Width>
				        <Height unit="Pixels">8784</Height>
				        <Resolution unit="DPI">600</Resolution>
				        <Depth unit="Bits">24</Depth>
				        <ViewRotation>1</ViewRotation>
				        <SampleColor>R:80 G:90 B:60</SampleColor>
				        <Pages>1</Pages>
				        <ColorSpace>RGB </ColorSpace>
				        <Compression>65537</Compression>
				        <PrimaryEncoding>TIFF (Uncompressed)</PrimaryEncoding>
				        <ColorProfile/>
			      </MediaProperties>
			      <AnnotationFields>
				        <Headline>Front Cover</Headline>
			      </AnnotationFields>
			      <MetaDataFields>
				        <Maker>i2s Digibook Scanner</Maker>
				        <Model>Suprascan 10000 RGB</Model>
				        <Software>Digibook Version :5, 5, 0, 23</Software>
				        <SourceURL/>
			      </MetaDataFields>
		    </MediaItem>
      <MediaItem>
			      <AssetProperties>
				        <Filename>m000000779_0002.tif</Filename>
				        <Filepath>lib_content37:EAM_Sheet:m000000779:m000000779_0002.tif</Filepath>
				        <UniqueID>5274</UniqueID>
				        <Label>0</Label>
				        <Rating>0</Rating>
				        <MediaType>TIFF</MediaType>
				        <FileSize unit="Bytes">179988873</FileSize>
				        <Created>2011:01:26 18:40:47</Created>
				        <Modified>2011:01:26 18:44:23</Modified>
				        <Added>2011:01:31 10:27:44</Added>
				        <Annotated>2011:02:02 16:08:36</Annotated>
			      </AssetProperties>
			      <MediaProperties>
				        <Width unit="Pixels">6912</Width>
				        <Height unit="Pixels">8680</Height>
				        <Resolution unit="DPI">600</Resolution>
				        <Depth unit="Bits">24</Depth>
				        <ViewRotation>1</ViewRotation>
				        <SampleColor>R:C0 G:D0 B:90</SampleColor>
				        <Pages>1</Pages>
				        <ColorSpace>RGB </ColorSpace>
				        <Compression>65537</Compression>
				        <PrimaryEncoding>TIFF (Uncompressed)</PrimaryEncoding>
				        <ColorProfile/>
			      </MediaProperties>
			      <AnnotationFields>
				        <Headline>2</Headline>
			      </AnnotationFields>
			      <MetaDataFields>
				        <Maker>i2s Digibook Scanner</Maker>
				        <Model>Suprascan 10000 RGB</Model>
				        <Software>Digibook Version :5, 5, 0, 23</Software>
				        <SourceURL/>
			      </MetaDataFields>
		    </MediaItem>
      <MediaItem>
			      <AssetProperties>
				        <Filename>m000000779_0003.tif</Filename>
				        <Filepath>lib_content37:EAM_Sheet:m000000779:m000000779_0003.tif</Filepath>
				        <UniqueID>5275</UniqueID>
				        <Label>0</Label>
				        <Rating>0</Rating>
				        <MediaType>TIFF</MediaType>
				        <FileSize unit="Bytes">185262729</FileSize>
				        <Created>2011:01:26 18:44:23</Created>
				        <Modified>2011:01:26 18:45:48</Modified>
				        <Added>2011:01:31 10:27:44</Added>
				        <Annotated>2011:02:02 16:08:36</Annotated>
			      </AssetProperties>
			      <MediaProperties>
				        <Width unit="Pixels">7056</Width>
				        <Height unit="Pixels">8752</Height>
				        <Resolution unit="DPI">600</Resolution>
				        <Depth unit="Bits">24</Depth>
				        <ViewRotation>1</ViewRotation>
				        <SampleColor>R:C0 G:D0 B:90</SampleColor>
				        <Pages>1</Pages>
				        <ColorSpace>RGB </ColorSpace>
				        <Compression>65537</Compression>
				        <PrimaryEncoding>TIFF (Uncompressed)</PrimaryEncoding>
				        <ColorProfile/>
			      </MediaProperties>
			      <AnnotationFields>
				        <Headline>3</Headline>
			      </AnnotationFields>
			      <MetaDataFields>
				        <Maker>i2s Digibook Scanner</Maker>
				        <Model>Suprascan 10000 RGB</Model>
				        <Software>Digibook Version :5, 5, 0, 23</Software>
				        <SourceURL/>
			      </MetaDataFields>
		    </MediaItem>
      <MediaItem>
			      <AssetProperties>
				        <Filename>m000000779_0004.tif</Filename>
				        <Filepath>lib_content37:EAM_Sheet:m000000779:m000000779_0004.tif</Filepath>
				        <UniqueID>5276</UniqueID>
				        <Label>0</Label>
				        <Rating>0</Rating>
				        <MediaType>TIFF</MediaType>
				        <FileSize unit="Bytes">181481865</FileSize>
				        <Created>2011:01:26 18:45:48</Created>
				        <Modified>2011:01:26 18:46:02</Modified>
				        <Added>2011:01:31 10:27:44</Added>
				        <Annotated>2011:02:02 16:08:37</Annotated>
			      </AssetProperties>
			      <MediaProperties>
				        <Width unit="Pixels">6912</Width>
				        <Height unit="Pixels">8752</Height>
				        <Resolution unit="DPI">600</Resolution>
				        <Depth unit="Bits">24</Depth>
				        <ViewRotation>1</ViewRotation>
				        <SampleColor>R:C0 G:D0 B:90</SampleColor>
				        <Pages>1</Pages>
				        <ColorSpace>RGB </ColorSpace>
				        <Compression>65537</Compression>
				        <PrimaryEncoding>TIFF (Uncompressed)</PrimaryEncoding>
				        <ColorProfile/>
			      </MediaProperties>
			      <AnnotationFields>
				        <Headline>4</Headline>
			      </AnnotationFields>
			      <MetaDataFields>
				        <Maker>i2s Digibook Scanner</Maker>
				        <Model>Suprascan 10000 RGB</Model>
				        <Software>Digibook Version :5, 5, 0, 23</Software>
				        <SourceURL/>
			      </MetaDataFields>
		    </MediaItem>
      <MediaItem>
			      <AssetProperties>
				        <Filename>m000000779_0005.tif</Filename>
				        <Filepath>lib_content37:EAM_Sheet:m000000779:m000000779_0005.tif</Filepath>
				        <UniqueID>5277</UniqueID>
				        <Label>0</Label>
				        <Rating>0</Rating>
				        <MediaType>TIFF</MediaType>
				        <FileSize unit="Bytes">178820169</FileSize>
				        <Created>2011:01:26 18:46:02</Created>
				        <Modified>2011:01:26 18:46:11</Modified>
				        <Added>2011:01:31 10:27:44</Added>
				        <Annotated>2011:02:02 16:08:37</Annotated>
			      </AssetProperties>
			      <MediaProperties>
				        <Width unit="Pixels">6792</Width>
				        <Height unit="Pixels">8776</Height>
				        <Resolution unit="DPI">600</Resolution>
				        <Depth unit="Bits">24</Depth>
				        <ViewRotation>1</ViewRotation>
				        <SampleColor>R:90 G:90 B:80</SampleColor>
				        <Pages>1</Pages>
				        <ColorSpace>RGB </ColorSpace>
				        <Compression>65537</Compression>
				        <PrimaryEncoding>TIFF (Uncompressed)</PrimaryEncoding>
				        <ColorProfile/>
			      </MediaProperties>
			      <AnnotationFields>
				        <Headline>5</Headline>
			      </AnnotationFields>
			      <MetaDataFields>
				        <Maker>i2s Digibook Scanner</Maker>
				        <Model>Suprascan 10000 RGB</Model>
				        <Software>Digibook Version :5, 5, 0, 23</Software>
				        <SourceURL/>
			      </MetaDataFields>
		    </MediaItem>
      <MediaItem>
			      <AssetProperties>
				        <Filename>m000000779_0006.tif</Filename>
				        <Filepath>lib_content37:EAM_Sheet:m000000779:m000000779_0006.tif</Filepath>
				        <UniqueID>5278</UniqueID>
				        <Label>0</Label>
				        <Rating>0</Rating>
				        <MediaType>TIFF</MediaType>
				        <FileSize unit="Bytes">180597129</FileSize>
				        <Created>2011:01:26 18:46:13</Created>
				        <Modified>2011:01:26 18:46:21</Modified>
				        <Added>2011:01:31 10:27:44</Added>
				        <Annotated>2011:02:02 16:08:38</Annotated>
			      </AssetProperties>
			      <MediaProperties>
				        <Width unit="Pixels">6816</Width>
				        <Height unit="Pixels">8832</Height>
				        <Resolution unit="DPI">600</Resolution>
				        <Depth unit="Bits">24</Depth>
				        <ViewRotation>1</ViewRotation>
				        <SampleColor>R:C0 G:D0 B:90</SampleColor>
				        <Pages>1</Pages>
				        <ColorSpace>RGB </ColorSpace>
				        <Compression>65537</Compression>
				        <PrimaryEncoding>TIFF (Uncompressed)</PrimaryEncoding>
				        <ColorProfile/>
			      </MediaProperties>
			      <AnnotationFields>
				        <Headline>Back Cover</Headline>
			      </AnnotationFields>
			      <MetaDataFields>
				        <Maker>i2s Digibook Scanner</Maker>
				        <Model>Suprascan 10000 RGB</Model>
				        <Software>Digibook Version :5, 5, 0, 23</Software>
				        <SourceURL/>
			      </MetaDataFields>
		    </MediaItem>
   </MediaItemList>
</CatalogType>