<?xml version="1.0" encoding="UTF-8" standalone="yes" ?><?expression media exportversion="1.0" appversion="1.0" ?><CatalogType>	<Catalog pathType = "MAC">m000002876</Catalog>	<MediaItemList>		<MediaItem>			<AssetProperties>				<Filename>m000002876_0001.tif</Filename>				<Filepath>DSSR:scan:10_raw:m000002876:m000002876_0001.tif</Filepath>				<UniqueID>2</UniqueID>				<Label>0</Label>				<Rating>0</Rating>				<MediaType>TIFF</MediaType>				<FileSize unit="Bytes">174573126</FileSize>				<Created>2008:07:09 13:12:52</Created>				<Modified>2008:07:09 13:13:00</Modified>				<Added>2008:07:09 15:35:31</Added>				<Annotated>2008:07:10 09:28:00</Annotated>			<ThumbnailSource>Thumbnails_(m000002876):m000002876_0001.jpg</ThumbnailSource>			</AssetProperties>			<MediaProperties>				<Width unit="Pixels">6704</Width>				<Height unit="Pixels">8680</Height>				<Resolution unit="DPI">600</Resolution>				<Depth unit="Bits">24</Depth>				<ViewRotation>1</ViewRotation>				<SampleColor>R:A0 G:C0 B:70</SampleColor>				<Pages>1</Pages>				<ColorSpace>RGB </ColorSpace>				<Compression>65537</Compression>				<PrimaryEncoding>TIFF (Uncompressed)</PrimaryEncoding>				<ColorProfile>Adobe RGB (1998)</ColorProfile>			</MediaProperties>			<AnnotationFields>				<Headline>Title Page</Headline>			</AnnotationFields>			<MetaDataFields>				<Maker>i2s Digibook Scanner</Maker>				<Model>Suprascan 10000 RGB</Model>				<Software>Digibook Version :5, 5, 8, 5</Software>				<SourceURL></SourceURL>			</MetaDataFields>		</MediaItem>		<MediaItem>			<AssetProperties>				<Filename>m000002876_0002.tif</Filename>				<Filepath>DSSR:scan:10_raw:m000002876:m000002876_0002.tif</Filepath>				<UniqueID>3</UniqueID>				<Label>0</Label>				<Rating>0</Rating>				<MediaType>TIFF</MediaType>				<FileSize unit="Bytes">174274758</FileSize>				<Created>2008:07:09 13:14:48</Created>				<Modified>2008:07:09 13:15:00</Modified>				<Added>2008:07:09 15:35:31</Added>				<Annotated>2008:07:10 09:28:02</Annotated>			<ThumbnailSource>Thumbnails_(m000002876):m000002876_0002.jpg</ThumbnailSource>			</AssetProperties>			<MediaProperties>				<Width unit="Pixels">6736</Width>				<Height unit="Pixels">8624</Height>				<Resolution unit="DPI">600</Resolution>				<Depth unit="Bits">24</Depth>				<ViewRotation>1</ViewRotation>				<SampleColor>R:B0 G:D0 B:80</SampleColor>				<Pages>1</Pages>				<ColorSpace>RGB </ColorSpace>				<Compression>65537</Compression>				<PrimaryEncoding>TIFF (Uncompressed)</PrimaryEncoding>				<ColorProfile>Adobe RGB (1998)</ColorProfile>			</MediaProperties>			<AnnotationFields>				<Headline>Page 2</Headline>			</AnnotationFields>			<MetaDataFields>				<Maker>i2s Digibook Scanner</Maker>				<Model>Suprascan 10000 RGB</Model>				<Software>Digibook Version :5, 5, 8, 5</Software>				<SourceURL></SourceURL>			</MetaDataFields>		</MediaItem>		<MediaItem>			<AssetProperties>				<Filename>m000002876_0003.tif</Filename>				<Filepath>DSSR:scan:10_raw:m000002876:m000002876_0003.tif</Filepath>				<UniqueID>4</UniqueID>				<Label>0</Label>				<Rating>0</Rating>				<MediaType>TIFF</MediaType>				<FileSize unit="Bytes">177336774</FileSize>				<Created>2008:07:09 13:15:00</Created>				<Modified>2008:07:09 13:15:11</Modified>				<Added>2008:07:09 15:35:31</Added>				<Annotated>2008:07:10 09:28:05</Annotated>			<ThumbnailSource>Thumbnails_(m000002876):m000002876_0003.jpg</ThumbnailSource>			</AssetProperties>			<MediaProperties>				<Width unit="Pixels">6848</Width>				<Height unit="Pixels">8632</Height>				<Resolution unit="DPI">600</Resolution>				<Depth unit="Bits">24</Depth>				<ViewRotation>1</ViewRotation>				<SampleColor>R:B0 G:D0 B:80</SampleColor>				<Pages>1</Pages>				<ColorSpace>RGB </ColorSpace>				<Compression>65537</Compression>				<PrimaryEncoding>TIFF (Uncompressed)</PrimaryEncoding>				<ColorProfile>Adobe RGB (1998)</ColorProfile>			</MediaProperties>			<AnnotationFields>				<Headline>Page 3</Headline>			</AnnotationFields>			<MetaDataFields>				<Maker>i2s Digibook Scanner</Maker>				<Model>Suprascan 10000 RGB</Model>				<Software>Digibook Version :5, 5, 8, 5</Software>				<SourceURL></SourceURL>			</MetaDataFields>		</MediaItem>		<MediaItem>			<AssetProperties>				<Filename>m000002876_0004.tif</Filename>				<Filepath>DSSR:scan:10_raw:m000002876:m000002876_0004.tif</Filepath>				<UniqueID>5</UniqueID>				<Label>0</Label>				<Rating>0</Rating>				<MediaType>TIFF</MediaType>				<FileSize unit="Bytes">173929542</FileSize>				<Created>2008:07:09 13:16:21</Created>				<Modified>2008:07:09 13:16:29</Modified>				<Added>2008:07:09 15:35:31</Added>				<Annotated>2008:07:10 09:28:11</Annotated>			<ThumbnailSource>Thumbnails_(m000002876):m000002876_0004.jpg</ThumbnailSource>			</AssetProperties>			<MediaProperties>				<Width unit="Pixels">6704</Width>				<Height unit="Pixels">8648</Height>				<Resolution unit="DPI">600</Resolution>				<Depth unit="Bits">24</Depth>				<ViewRotation>1</ViewRotation>				<SampleColor>R:B0 G:D0 B:90</SampleColor>				<Pages>1</Pages>				<ColorSpace>RGB </ColorSpace>				<Compression>65537</Compression>				<PrimaryEncoding>TIFF (Uncompressed)</PrimaryEncoding>				<ColorProfile>Adobe RGB (1998)</ColorProfile>			</MediaProperties>			<AnnotationFields>				<Headline>Back Page</Headline>			</AnnotationFields>			<MetaDataFields>				<Maker>i2s Digibook Scanner</Maker>				<Model>Suprascan 10000 RGB</Model>				<Software>Digibook Version :5, 5, 8, 5</Software>				<SourceURL></SourceURL>			</MetaDataFields>		</MediaItem>	</MediaItemList></CatalogType>