<?xml version="1.0" encoding="UTF-8" standalone="yes" ?><?expression media exportversion="1.0" appversion="1.0" ?><CatalogType>	<Catalog pathType = "MAC">m000003480</Catalog>	<MediaItemList>		<MediaItem>			<AssetProperties>				<Filename>m000003480_0001.tif</Filename>				<Filepath>DSSR:scan:10_raw:m000003480:m000003480_0001.tif</Filepath>				<UniqueID>1</UniqueID>				<Label>0</Label>				<Rating>0</Rating>				<MediaType>TIFF</MediaType>				<FileSize unit="Bytes">131377352</FileSize>				<Created>2008:07:21 14:25:50</Created>				<Modified>2008:07:21 14:25:55</Modified>				<Added>2008:07:21 15:20:23</Added>				<Annotated>2008:07:22 10:31:20</Annotated>			<ThumbnailSource>Thumbnails_(m000003480):m000003480_0001.jpg</ThumbnailSource>			</AssetProperties>			<MediaProperties>				<Width unit="Pixels">5976</Width>				<Height unit="Pixels">7328</Height>				<Resolution unit="DPI">600</Resolution>				<Depth unit="Bits">24</Depth>				<ViewRotation>1</ViewRotation>				<SampleColor>R:80 G:90 B:60</SampleColor>				<Pages>1</Pages>				<ColorSpace>RGB </ColorSpace>				<Compression>65537</Compression>				<PrimaryEncoding>TIFF (Uncompressed)</PrimaryEncoding>				<ColorProfile>Adobe RGB (1998)</ColorProfile>			</MediaProperties>			<AnnotationFields>				<Headline>Title Page</Headline>			</AnnotationFields>			<MetaDataFields>				<Maker>i2s Digibook Scanner</Maker>				<Model>Suprascan 10000 RGB</Model>				<Software>Digibook Version :5, 5, 0, 23</Software>				<SourceURL></SourceURL>			</MetaDataFields>		</MediaItem>		<MediaItem>			<AssetProperties>				<Filename>m000003480_0002.tif</Filename>				<Filepath>DSSR:scan:10_raw:m000003480:m000003480_0002.tif</Filepath>				<UniqueID>4</UniqueID>				<Label>0</Label>				<Rating>0</Rating>				<MediaType>TIFF</MediaType>				<FileSize unit="Bytes">133219208</FileSize>				<Created>2008:07:21 14:27:26</Created>				<Modified>2008:07:21 14:27:58</Modified>				<Added>2008:07:21 15:20:23</Added>				<Annotated>2008:07:22 10:32:10</Annotated>			<ThumbnailSource>Thumbnails_(m000003480):m000003480_0002.jpg</ThumbnailSource>			</AssetProperties>			<MediaProperties>				<Width unit="Pixels">6040</Width>				<Height unit="Pixels">7352</Height>				<Resolution unit="DPI">600</Resolution>				<Depth unit="Bits">24</Depth>				<ViewRotation>1</ViewRotation>				<SampleColor>R:90 G:A0 B:70</SampleColor>				<Pages>1</Pages>				<ColorSpace>RGB </ColorSpace>				<Compression>65537</Compression>				<PrimaryEncoding>TIFF (Uncompressed)</PrimaryEncoding>				<ColorProfile>Adobe RGB (1998)</ColorProfile>			</MediaProperties>			<AnnotationFields>				<Headline>Page 2</Headline>			</AnnotationFields>			<MetaDataFields>				<Maker>i2s Digibook Scanner</Maker>				<Model>Suprascan 10000 RGB</Model>				<Software>Digibook Version :5, 5, 0, 23</Software>				<SourceURL></SourceURL>			</MetaDataFields>		</MediaItem>		<MediaItem>			<AssetProperties>				<Filename>m000003480_0003.tif</Filename>				<Filepath>DSSR:scan:10_raw:m000003480:m000003480_0003.tif</Filepath>				<UniqueID>2</UniqueID>				<Label>0</Label>				<Rating>0</Rating>				<MediaType>TIFF</MediaType>				<FileSize unit="Bytes">134378888</FileSize>				<Created>2008:07:21 14:27:58</Created>				<Modified>2008:07:21 14:28:17</Modified>				<Added>2008:07:21 15:20:23</Added>				<Annotated>2008:07:22 10:32:16</Annotated>			<ThumbnailSource>Thumbnails_(m000003480):m000003480_0003.jpg</ThumbnailSource>			</AssetProperties>			<MediaProperties>				<Width unit="Pixels">6040</Width>				<Height unit="Pixels">7416</Height>				<Resolution unit="DPI">600</Resolution>				<Depth unit="Bits">24</Depth>				<ViewRotation>1</ViewRotation>				<SampleColor>R:90 G:A0 B:70</SampleColor>				<Pages>1</Pages>				<ColorSpace>RGB </ColorSpace>				<Compression>65537</Compression>				<PrimaryEncoding>TIFF (Uncompressed)</PrimaryEncoding>				<ColorProfile>Adobe RGB (1998)</ColorProfile>			</MediaProperties>			<AnnotationFields>				<Headline>Page 3</Headline>			</AnnotationFields>			<MetaDataFields>				<Maker>i2s Digibook Scanner</Maker>				<Model>Suprascan 10000 RGB</Model>				<Software>Digibook Version :5, 5, 0, 23</Software>				<SourceURL></SourceURL>			</MetaDataFields>		</MediaItem>		<MediaItem>			<AssetProperties>				<Filename>m000003480_0004.tif</Filename>				<Filepath>DSSR:scan:10_raw:m000003480:m000003480_0004.tif</Filepath>				<UniqueID>3</UniqueID>				<Label>0</Label>				<Rating>0</Rating>				<MediaType>TIFF</MediaType>				<FileSize unit="Bytes">131184622</FileSize>				<Created>2008:07:21 14:29:12</Created>				<Modified>2008:07:22 10:33:54</Modified>				<Added>2008:07:21 15:20:23</Added>				<Annotated>2008:07:22 10:32:19</Annotated>			<ThumbnailSource>Thumbnails_(m000003480):m000003480_0004.jpg</ThumbnailSource>			</AssetProperties>			<MediaProperties>				<Width unit="Pixels">5987</Width>				<Height unit="Pixels">7299</Height>				<Resolution unit="DPI">600</Resolution>				<Depth unit="Bits">24</Depth>				<ViewRotation>1</ViewRotation>				<SampleColor>R:50 G:70 B:30</SampleColor>				<Pages>1</Pages>				<ColorSpace>RGB </ColorSpace>				<Compression>65537</Compression>				<PrimaryEncoding>TIFF (Uncompressed)</PrimaryEncoding>				<ColorProfile>Adobe RGB (1998)</ColorProfile>			</MediaProperties>			<AnnotationFields>				<Headline>Back Page</Headline>			</AnnotationFields>			<MetaDataFields>				<Maker>i2s Digibook Scanner</Maker>				<Model>Suprascan 10000 RGB</Model>				<Software>Adobe Photoshop CS2 Macintosh</Software>				<SourceURL></SourceURL>			</MetaDataFields>		</MediaItem>	</MediaItemList></CatalogType>