<?xml version="1.0" encoding="UTF-8" standalone="yes" ?><?expression media exportversion="1.0" appversion="1.0" ?><CatalogType>	<Catalog pathType = "MAC">m000003481</Catalog>	<MediaItemList>		<MediaItem>			<AssetProperties>				<Filename>m000003481_0001.tif</Filename>				<Filepath>DSSR:scan:10_raw:m000003481:m000003481_0001.tif</Filepath>				<UniqueID>1</UniqueID>				<Label>0</Label>				<Rating>0</Rating>				<MediaType>TIFF</MediaType>				<FileSize unit="Bytes">157383752</FileSize>				<Created>2008:07:21 14:32:30</Created>				<Modified>2008:07:21 14:33:12</Modified>				<Added>2008:07:21 15:30:52</Added>				<Annotated>2008:07:22 10:44:44</Annotated>			<ThumbnailSource>Thumbnails_(m000003481):m000003481_0001.jpg</ThumbnailSource>			</AssetProperties>			<MediaProperties>				<Width unit="Pixels">6448</Width>				<Height unit="Pixels">8136</Height>				<Resolution unit="DPI">600</Resolution>				<Depth unit="Bits">24</Depth>				<ViewRotation>1</ViewRotation>				<SampleColor>R:60 G:80 B:40</SampleColor>				<Pages>1</Pages>				<ColorSpace>RGB </ColorSpace>				<Compression>65537</Compression>				<PrimaryEncoding>TIFF (Uncompressed)</PrimaryEncoding>				<ColorProfile>Adobe RGB (1998)</ColorProfile>			</MediaProperties>			<AnnotationFields>				<Headline>Title Page</Headline>			</AnnotationFields>			<MetaDataFields>				<Maker>i2s Digibook Scanner</Maker>				<Model>Suprascan 10000 RGB</Model>				<Software>Digibook Version :5, 5, 0, 23</Software>				<SourceURL></SourceURL>			</MetaDataFields>		</MediaItem>		<MediaItem>			<AssetProperties>				<Filename>m000003481_0002.tif</Filename>				<Filepath>DSSR:scan:10_raw:m000003481:m000003481_0002.tif</Filepath>				<UniqueID>2</UniqueID>				<Label>0</Label>				<Rating>0</Rating>				<MediaType>TIFF</MediaType>				<FileSize unit="Bytes">151949117</FileSize>				<Created>2008:07:21 14:34:09</Created>				<Modified>2008:07:22 10:47:53</Modified>				<Added>2008:07:21 15:30:52</Added>				<Annotated>2008:07:22 10:45:01</Annotated>			<ThumbnailSource>Thumbnails_(m000003481):m000003481_0002.jpg</ThumbnailSource>			</AssetProperties>			<MediaProperties>				<Width unit="Pixels">6195</Width>				<Height unit="Pixels">8171</Height>				<Resolution unit="DPI">600</Resolution>				<Depth unit="Bits">24</Depth>				<ViewRotation>1</ViewRotation>				<SampleColor>R:70 G:90 B:50</SampleColor>				<Pages>1</Pages>				<ColorSpace>RGB </ColorSpace>				<Compression>65537</Compression>				<PrimaryEncoding>TIFF (Uncompressed)</PrimaryEncoding>				<ColorProfile>Adobe RGB (1998)</ColorProfile>			</MediaProperties>			<AnnotationFields>				<Headline>Page 2</Headline>			</AnnotationFields>			<MetaDataFields>				<Maker>i2s Digibook Scanner</Maker>				<Model>Suprascan 10000 RGB</Model>				<Software>Digibook Version :5, 5, 0, 23</Software>				<SourceURL></SourceURL>			</MetaDataFields>		</MediaItem>		<MediaItem>			<AssetProperties>				<Filename>m000003481_0003.tif</Filename>				<Filepath>DSSR:scan:10_raw:m000003481:m000003481_0003.tif</Filepath>				<UniqueID>3</UniqueID>				<Label>0</Label>				<Rating>0</Rating>				<MediaType>TIFF</MediaType>				<FileSize unit="Bytes">151174382</FileSize>				<Created>2008:07:21 14:34:17</Created>				<Modified>2008:07:22 10:49:36</Modified>				<Added>2008:07:21 15:30:52</Added>				<Annotated>2008:07:22 10:45:10</Annotated>			<ThumbnailSource>Thumbnails_(m000003481):m000003481_0003.jpg</ThumbnailSource>			</AssetProperties>			<MediaProperties>				<Width unit="Pixels">6256</Width>				<Height unit="Pixels">8050</Height>				<Resolution unit="DPI">600</Resolution>				<Depth unit="Bits">24</Depth>				<ViewRotation>1</ViewRotation>				<SampleColor>R:70 G:80 B:50</SampleColor>				<Pages>1</Pages>				<ColorSpace>RGB </ColorSpace>				<Compression>65537</Compression>				<PrimaryEncoding>TIFF (Uncompressed)</PrimaryEncoding>				<ColorProfile>Adobe RGB (1998)</ColorProfile>			</MediaProperties>			<AnnotationFields>				<Headline>Page 3</Headline>			</AnnotationFields>			<MetaDataFields>				<Maker>i2s Digibook Scanner</Maker>				<Model>Suprascan 10000 RGB</Model>				<Software>Adobe Photoshop CS2 Macintosh</Software>				<SourceURL></SourceURL>			</MetaDataFields>		</MediaItem>		<MediaItem>			<AssetProperties>				<Filename>m000003481_0004.tif</Filename>				<Filepath>DSSR:scan:10_raw:m000003481:m000003481_0004.tif</Filepath>				<UniqueID>4</UniqueID>				<Label>0</Label>				<Rating>0</Rating>				<MediaType>TIFF</MediaType>				<FileSize unit="Bytes">153127417</FileSize>				<Created>2008:07:21 14:35:50</Created>				<Modified>2008:07:22 10:51:37</Modified>				<Added>2008:07:21 15:30:52</Added>				<Annotated>2008:07:22 10:45:17</Annotated>			<ThumbnailSource>Thumbnails_(m000003481):m000003481_0004.jpg</ThumbnailSource>			</AssetProperties>			<MediaProperties>				<Width unit="Pixels">6340</Width>				<Height unit="Pixels">8046</Height>				<Resolution unit="DPI">600</Resolution>				<Depth unit="Bits">24</Depth>				<ViewRotation>1</ViewRotation>				<SampleColor>R:70 G:90 B:50</SampleColor>				<Pages>1</Pages>				<ColorSpace>RGB </ColorSpace>				<Compression>65537</Compression>				<PrimaryEncoding>TIFF (Uncompressed)</PrimaryEncoding>				<ColorProfile>Adobe RGB (1998)</ColorProfile>			</MediaProperties>			<AnnotationFields>				<Headline>Back Page</Headline>			</AnnotationFields>			<MetaDataFields>				<Maker>i2s Digibook Scanner</Maker>				<Model>Suprascan 10000 RGB</Model>				<Software>Digibook Version :5, 5, 0, 23</Software>				<SourceURL></SourceURL>			</MetaDataFields>		</MediaItem>	</MediaItemList></CatalogType>